<?xml version="1.0" encoding="UTF-8"?>

<!-- generated on Sat Apr 28 22:34:39 2018 by SUMO Version 0.32.0
<?xml version="1.0" encoding="UTF-8"?>

<configuration xmlns:xsi="http://www.w3.org/2001/XMLSchema-instance" xsi:noNamespaceSchemaLocation="http://sumo.dlr.de/xsd/sumoConfiguration.xsd">

    <input>
        <net-file value="mapgrid.net.xml"/>
        <route-files value="route.rou.xml"/>
    </input>

    <output>
        <fcd-output value="skenario.xml"/>
    </output>

    <time>
        <begin value="0"/>
        <end value="250"/>
        <step-length value="3"/>
    </time>

    <gui_only>
        <tracker-interval value="3"/>
    </gui_only>

</configuration>
-->

<fcd-export xmlns:xsi="http://www.w3.org/2001/XMLSchema-instance" xsi:noNamespaceSchemaLocation="http://sumo.dlr.de/xsd/fcd_file.xsd">
    <timestep time="0.00">
        <vehicle id="0" x="684.35" y="602.40" angle="180.00" type="DEFAULT_VEHTYPE" speed="32.09" pos="78.85" lane="7/7to7/6_0" slope="0.00"/>
        <vehicle id="1" x="981.65" y="165.81" angle="0.00" type="DEFAULT_VEHTYPE" speed="16.49" pos="63.06" lane="10/1to10/2_0" slope="0.00"/>
    </timestep>
    <timestep time="3.00">
        <vehicle id="0" x="605.41" y="589.65" angle="270.00" type="DEFAULT_VEHTYPE" speed="30.16" pos="75.84" lane="7/6to6/6_0" slope="0.00"/>
        <vehicle id="1" x="958.20" y="197.65" angle="270.00" type="DEFAULT_VEHTYPE" speed="17.60" pos="17.05" lane="10/2to9/2_0" slope="0.00"/>
        <vehicle id="2" x="883.65" y="252.96" angle="0.00" type="DEFAULT_VEHTYPE" speed="19.20" pos="52.21" lane="9/2to9/3_0" slope="0.00"/>
        <vehicle id="3" x="596.61" y="-1.65" angle="90.00" type="DEFAULT_VEHTYPE" speed="29.45" pos="3.86" lane="6/0to7/0_0" slope="0.00"/>
        <vehicle id="4" x="756.53" y="194.35" angle="90.00" type="DEFAULT_VEHTYPE" speed="15.81" pos="65.78" lane="7/2to8/2_0" slope="0.00"/>
        <vehicle id="5" x="169.35" y="197.65" angle="270.00" type="DEFAULT_VEHTYPE" speed="26.77" pos="21.90" lane="2/2to1/2_0" slope="0.00"/>
    </timestep>
    <timestep time="6.00">
        <vehicle id="0" x="555.43" y="589.65" angle="270.00" type="DEFAULT_VEHTYPE" speed="16.66" pos="27.82" lane="6/6to5/6_0" slope="0.00"/>
        <vehicle id="1" x="888.37" y="197.65" angle="270.00" type="DEFAULT_VEHTYPE" speed="23.28" pos="86.88" lane="10/2to9/2_0" slope="0.00"/>
        <vehicle id="2" x="867.67" y="295.65" angle="270.00" type="DEFAULT_VEHTYPE" speed="18.73" pos="9.58" lane="9/3to8/3_0" slope="0.00"/>
        <vehicle id="3" x="679.30" y="-1.65" angle="90.00" type="DEFAULT_VEHTYPE" speed="27.56" pos="86.55" lane="6/0to7/0_0" slope="0.00"/>
        <vehicle id="4" x="764.91" y="197.65" angle="270.00" type="DEFAULT_VEHTYPE" speed="13.96" pos="14.34" lane="8/2to7/2_0" slope="0.00"/>
        <vehicle id="5" x="99.65" y="209.33" angle="0.00" type="DEFAULT_VEHTYPE" speed="26.73" pos="8.58" lane="1/2to1/3_0" slope="0.00"/>
        <vehicle id="6" x="239.13" y="1.65" angle="270.00" type="DEFAULT_VEHTYPE" speed="50.00" pos="50.12" lane="3/0to2/0_0" slope="0.00"/>
        <vehicle id="7" x="461.84" y="1.65" angle="270.00" type="DEFAULT_VEHTYPE" speed="50.00" pos="23.41" lane="5/0to4/0_0" slope="0.00"/>
        <vehicle id="8" x="577.92" y="393.65" angle="270.00" type="DEFAULT_VEHTYPE" speed="29.24" pos="5.33" lane="6/4to5/4_0" slope="0.00"/>
    </timestep>
    <timestep time="9.00">
        <vehicle id="0" x="490.34" y="588.28" angle="253.80" type="DEFAULT_VEHTYPE" speed="21.80" pos="4.71" lane=":5/6_6_0" slope="0.00"/>
        <vehicle id="1" x="805.39" y="197.65" angle="270.00" type="DEFAULT_VEHTYPE" speed="27.66" pos="71.86" lane="9/2to8/2_0" slope="0.00"/>
        <vehicle id="10" x="393.65" y="333.85" angle="0.00" type="DEFAULT_VEHTYPE" speed="23.48" pos="35.10" lane="4/3to4/4_0" slope="0.00"/>
        <vehicle id="11" x="535.08" y="687.65" angle="270.00" type="DEFAULT_VEHTYPE" speed="20.21" pos="48.17" lane="6/7to5/7_0" slope="0.00"/>
        <vehicle id="2" x="791.68" y="295.65" angle="270.00" type="DEFAULT_VEHTYPE" speed="25.33" pos="85.57" lane="9/3to8/3_0" slope="0.00"/>
        <vehicle id="3" x="687.65" y="34.67" angle="0.00" type="DEFAULT_VEHTYPE" speed="14.06" pos="29.92" lane="7/0to7/1_0" slope="0.00"/>
        <vehicle id="4" x="705.62" y="197.65" angle="270.00" type="DEFAULT_VEHTYPE" speed="19.76" pos="73.63" lane="8/2to7/2_0" slope="0.00"/>
        <vehicle id="5" x="99.65" y="312.36" angle="0.00" type="DEFAULT_VEHTYPE" speed="34.35" pos="13.61" lane="1/3to1/4_0" slope="0.00"/>
        <vehicle id="6" x="197.65" y="103.95" angle="0.00" type="DEFAULT_VEHTYPE" speed="47.53" pos="1.20" lane="2/1to2/2_0" slope="0.00"/>
        <vehicle id="7" x="393.65" y="73.67" angle="0.00" type="DEFAULT_VEHTYPE" speed="46.34" pos="68.92" lane="4/0to4/1_0" slope="0.00"/>
        <vehicle id="8" x="499.89" y="393.65" angle="270.00" type="DEFAULT_VEHTYPE" speed="26.01" pos="83.36" lane="6/4to5/4_0" slope="0.00"/>
        <vehicle id="9" x="491.65" y="867.30" angle="0.00" type="DEFAULT_VEHTYPE" speed="3.31" pos="78.55" lane="5/8to5/9_0" slope="0.00"/>
    </timestep>
    <timestep time="12.00">
        <vehicle id="0" x="488.35" y="511.27" angle="180.00" type="DEFAULT_VEHTYPE" speed="25.86" pos="71.98" lane="5/6to5/5_0" slope="0.00"/>
        <vehicle id="1" x="762.90" y="197.65" angle="270.00" type="DEFAULT_VEHTYPE" speed="14.16" pos="16.35" lane="8/2to7/2_0" slope="0.00"/>
        <vehicle id="10" x="378.18" y="393.65" angle="270.00" type="DEFAULT_VEHTYPE" speed="24.27" pos="9.07" lane="4/4to3/4_0" slope="0.00"/>
        <vehicle id="11" x="505.33" y="684.35" angle="90.00" type="DEFAULT_VEHTYPE" speed="18.58" pos="10.58" lane="5/7to6/7_0" slope="0.00"/>
        <vehicle id="12" x="203.89" y="99.65" angle="270.00" type="DEFAULT_VEHTYPE" speed="1.05" pos="85.36" lane="3/1to2/1_0" slope="0.00"/>
        <vehicle id="13" x="363.88" y="589.65" angle="270.00" type="DEFAULT_VEHTYPE" speed="26.41" pos="23.37" lane="4/6to3/6_0" slope="0.00"/>
        <vehicle id="2" x="696.77" y="295.65" angle="270.00" type="DEFAULT_VEHTYPE" speed="31.63" pos="82.48" lane="8/3to7/3_0" slope="0.00"/>
        <vehicle id="3" x="687.65" y="98.40" angle="0.00" type="DEFAULT_VEHTYPE" speed="21.24" pos="5.15" lane=":7/1_9_0" slope="0.00"/>
        <vehicle id="4" x="684.35" y="177.76" angle="180.00" type="DEFAULT_VEHTYPE" speed="12.89" pos="13.49" lane="7/2to7/1_0" slope="0.00"/>
        <vehicle id="5" x="99.65" y="438.45" angle="0.00" type="DEFAULT_VEHTYPE" speed="42.03" pos="41.70" lane="1/4to1/5_0" slope="0.00"/>
        <vehicle id="6" x="197.65" y="245.94" angle="0.00" type="DEFAULT_VEHTYPE" speed="47.33" pos="45.19" lane="2/2to2/3_0" slope="0.00"/>
        <vehicle id="7" x="393.65" y="219.80" angle="0.00" type="DEFAULT_VEHTYPE" speed="48.71" pos="19.05" lane="4/2to4/3_0" slope="0.00"/>
        <vehicle id="8" x="491.65" y="424.14" angle="0.00" type="DEFAULT_VEHTYPE" speed="12.51" pos="27.39" lane="5/4to5/5_0" slope="0.00"/>
        <vehicle id="9" x="473.64" y="883.65" angle="270.00" type="DEFAULT_VEHTYPE" speed="10.63" pos="11.61" lane="5/9to4/9_0" slope="0.00"/>
    </timestep>
    <timestep time="15.00">
        <vehicle id="0" x="488.35" y="412.25" angle="180.00" type="DEFAULT_VEHTYPE" speed="33.01" pos="73.00" lane="5/5to5/4_0" slope="0.00"/>
        <vehicle id="1" x="702.78" y="197.65" angle="270.00" type="DEFAULT_VEHTYPE" speed="20.04" pos="76.47" lane="8/2to7/2_0" slope="0.00"/>
        <vehicle id="10" x="293.88" y="393.65" angle="270.00" type="DEFAULT_VEHTYPE" speed="28.10" pos="4.87" lane=":3/4_5_0" slope="0.00"/>
        <vehicle id="11" x="581.20" y="684.35" angle="90.00" type="DEFAULT_VEHTYPE" speed="25.29" pos="86.45" lane="5/7to6/7_0" slope="0.00"/>
        <vehicle id="12" x="197.65" y="114.75" angle="0.00" type="DEFAULT_VEHTYPE" speed="6.71" pos="12.00" lane="2/1to2/2_0" slope="0.00"/>
        <vehicle id="13" x="295.59" y="589.65" angle="270.00" type="DEFAULT_VEHTYPE" speed="22.76" pos="3.16" lane=":3/6_5_0" slope="0.00"/>
        <vehicle id="14" x="675.32" y="295.65" angle="270.00" type="DEFAULT_VEHTYPE" speed="19.96" pos="5.93" lane="7/3to6/3_0" slope="0.00"/>
        <vehicle id="15" x="-1.65" y="371.41" angle="180.00" type="DEFAULT_VEHTYPE" speed="27.74" pos="15.84" lane="0/4to0/3_0" slope="0.00"/>
        <vehicle id="16" x="593.43" y="491.65" angle="270.00" type="DEFAULT_VEHTYPE" speed="50.00" pos="87.82" lane="7/5to6/5_0" slope="0.00"/>
        <vehicle id="2" x="642.37" y="295.65" angle="270.00" type="DEFAULT_VEHTYPE" speed="18.13" pos="38.88" lane="7/3to6/3_0" slope="0.00"/>
        <vehicle id="3" x="687.65" y="178.74" angle="0.00" type="DEFAULT_VEHTYPE" speed="26.78" pos="75.99" lane="7/1to7/2_0" slope="0.00"/>
        <vehicle id="4" x="684.35" y="126.62" angle="180.00" type="DEFAULT_VEHTYPE" speed="17.05" pos="64.63" lane="7/2to7/1_0" slope="0.00"/>
        <vehicle id="5" x="99.65" y="574.57" angle="0.00" type="DEFAULT_VEHTYPE" speed="45.37" pos="79.82" lane="1/5to1/6_0" slope="0.00"/>
        <vehicle id="6" x="197.65" y="393.79" angle="0.00" type="DEFAULT_VEHTYPE" speed="49.28" pos="6.54" lane=":2/4_9_0" slope="0.00"/>
        <vehicle id="7" x="393.65" y="362.29" angle="0.00" type="DEFAULT_VEHTYPE" speed="47.50" pos="63.54" lane="4/3to4/4_0" slope="0.00"/>
        <vehicle id="8" x="491.65" y="481.46" angle="0.00" type="DEFAULT_VEHTYPE" speed="19.11" pos="84.71" lane="5/4to5/5_0" slope="0.00"/>
        <vehicle id="9" x="418.69" y="883.65" angle="270.00" type="DEFAULT_VEHTYPE" speed="18.32" pos="66.56" lane="5/9to4/9_0" slope="0.00"/>
    </timestep>
    <timestep time="18.00">
        <vehicle id="0" x="488.35" y="296.67" angle="180.00" type="DEFAULT_VEHTYPE" speed="38.53" pos="2.08" lane=":5/3_1_0" slope="0.00"/>
        <vehicle id="1" x="683.15" y="197.65" angle="270.00" type="DEFAULT_VEHTYPE" speed="6.54" pos="7.60" lane=":7/2_5_0" slope="0.00"/>
        <vehicle id="10" x="202.22" y="393.65" angle="270.00" type="DEFAULT_VEHTYPE" speed="30.55" pos="87.03" lane="3/4to2/4_0" slope="0.00"/>
        <vehicle id="11" x="668.91" y="684.35" angle="90.00" type="DEFAULT_VEHTYPE" speed="29.24" pos="76.16" lane="6/7to7/7_0" slope="0.00"/>
        <vehicle id="12" x="197.65" y="154.75" angle="0.00" type="DEFAULT_VEHTYPE" speed="13.33" pos="52.00" lane="2/1to2/2_0" slope="0.00"/>
        <vehicle id="13" x="205.13" y="589.65" angle="270.00" type="DEFAULT_VEHTYPE" speed="30.15" pos="84.12" lane="3/6to2/6_0" slope="0.00"/>
        <vehicle id="14" x="621.43" y="295.65" angle="270.00" type="DEFAULT_VEHTYPE" speed="17.96" pos="59.82" lane="7/3to6/3_0" slope="0.00"/>
        <vehicle id="15" x="-0.93" y="297.67" angle="171.49" type="DEFAULT_VEHTYPE" speed="24.65" pos="1.30" lane=":0/3_2_0" slope="0.00"/>
        <vehicle id="17" x="674.60" y="586.35" angle="90.00" type="DEFAULT_VEHTYPE" speed="2.21" pos="81.85" lane="6/6to7/6_0" slope="0.00"/>
        <vehicle id="18" x="930.35" y="96.35" angle="90.00" type="DEFAULT_VEHTYPE" speed="21.35" pos="43.60" lane="9/1to10/1_0" slope="0.00"/>
        <vehicle id="19" x="785.65" y="924.37" angle="0.00" type="DEFAULT_VEHTYPE" speed="22.84" pos="37.62" lane="8/9to8/10_0" slope="0.00"/>
        <vehicle id="2" x="579.42" y="295.65" angle="270.00" type="DEFAULT_VEHTYPE" speed="20.98" pos="3.83" lane="6/3to5/3_0" slope="0.00"/>
        <vehicle id="20" x="912.78" y="981.65" angle="270.00" type="DEFAULT_VEHTYPE" speed="35.08" pos="63.97" lane="10/10to9/10_0" slope="0.00"/>
        <vehicle id="3" x="687.65" y="272.83" angle="0.00" type="DEFAULT_VEHTYPE" speed="31.36" pos="72.08" lane="7/2to7/3_0" slope="0.00"/>
        <vehicle id="5" x="99.65" y="670.19" angle="0.00" type="DEFAULT_VEHTYPE" speed="31.87" pos="77.44" lane="1/6to1/7_0" slope="0.00"/>
        <vehicle id="6" x="197.65" y="539.52" angle="0.00" type="DEFAULT_VEHTYPE" speed="48.58" pos="44.77" lane="2/5to2/6_0" slope="0.00"/>
        <vehicle id="7" x="393.65" y="500.86" angle="0.00" type="DEFAULT_VEHTYPE" speed="46.19" pos="6.11" lane="4/5to4/6_0" slope="0.00"/>
        <vehicle id="8" x="491.65" y="559.70" angle="0.00" type="DEFAULT_VEHTYPE" speed="26.08" pos="64.95" lane="5/5to5/6_0" slope="0.00"/>
        <vehicle id="9" x="390.35" y="867.71" angle="180.00" type="DEFAULT_VEHTYPE" speed="13.93" pos="9.54" lane="4/9to4/8_0" slope="0.00"/>
    </timestep>
    <timestep time="21.00">
        <vehicle id="0" x="488.35" y="158.88" angle="180.00" type="DEFAULT_VEHTYPE" speed="45.93" pos="32.37" lane="5/2to5/1_0" slope="0.00"/>
        <vehicle id="1" x="651.50" y="197.65" angle="270.00" type="DEFAULT_VEHTYPE" speed="10.55" pos="29.75" lane="7/2to6/2_0" slope="0.00"/>
        <vehicle id="10" x="194.35" y="287.27" angle="180.00" type="DEFAULT_VEHTYPE" speed="37.26" pos="1.98" lane="2/3to2/2_0" slope="0.00"/>
        <vehicle id="11" x="716.12" y="684.35" angle="90.00" type="DEFAULT_VEHTYPE" speed="15.74" pos="25.37" lane="7/7to8/7_0" slope="0.00"/>
        <vehicle id="12" x="197.65" y="207.92" angle="0.00" type="DEFAULT_VEHTYPE" speed="17.72" pos="7.17" lane="2/2to2/3_0" slope="0.00"/>
        <vehicle id="13" x="155.17" y="589.65" angle="270.00" type="DEFAULT_VEHTYPE" speed="16.65" pos="36.08" lane="2/6to1/6_0" slope="0.00"/>
        <vehicle id="14" x="574.95" y="295.65" angle="270.00" type="DEFAULT_VEHTYPE" speed="15.49" pos="8.30" lane="6/3to5/3_0" slope="0.00"/>
        <vehicle id="15" x="1.65" y="391.13" angle="0.00" type="DEFAULT_VEHTYPE" speed="31.97" pos="3.88" lane=":0/4_7_0" slope="0.00"/>
        <vehicle id="17" x="679.76" y="586.35" angle="90.00" type="DEFAULT_VEHTYPE" speed="1.72" pos="87.01" lane="6/6to7/6_0" slope="0.00"/>
        <vehicle id="18" x="981.65" y="107.16" angle="0.96" type="DEFAULT_VEHTYPE" speed="19.87" pos="4.41" lane="10/1to10/2_0" slope="0.00"/>
        <vehicle id="19" x="782.35" y="972.81" angle="203.89" type="DEFAULT_VEHTYPE" speed="19.38" pos="2.44" lane="8/10to8/9_0" slope="0.00"/>
        <vehicle id="2" x="497.07" y="295.65" angle="270.00" type="DEFAULT_VEHTYPE" speed="27.45" pos="86.18" lane="6/3to5/3_0" slope="0.00"/>
        <vehicle id="20" x="813.68" y="981.65" angle="270.00" type="DEFAULT_VEHTYPE" speed="33.03" pos="63.57" lane="9/10to8/10_0" slope="0.00"/>
        <vehicle id="21" x="344.77" y="393.65" angle="270.00" type="DEFAULT_VEHTYPE" speed="21.63" pos="42.48" lane="4/4to3/4_0" slope="0.00"/>
        <vehicle id="22" x="425.48" y="295.65" angle="270.00" type="DEFAULT_VEHTYPE" speed="17.31" pos="59.77" lane="5/3to4/3_0" slope="0.00"/>
        <vehicle id="23" x="679.32" y="684.35" angle="90.00" type="DEFAULT_VEHTYPE" speed="0.64" pos="86.57" lane="6/7to7/7_0" slope="0.00"/>
        <vehicle id="3" x="687.65" y="382.13" angle="0.00" type="DEFAULT_VEHTYPE" speed="36.43" pos="83.38" lane="7/3to7/4_0" slope="0.00"/>
        <vehicle id="5" x="59.51" y="687.65" angle="270.00" type="DEFAULT_VEHTYPE" speed="18.37" pos="33.74" lane="1/7to0/7_0" slope="0.00"/>
        <vehicle id="6" x="197.65" y="675.22" angle="0.00" type="DEFAULT_VEHTYPE" speed="45.23" pos="82.47" lane="2/6to2/7_0" slope="0.00"/>
        <vehicle id="7" x="393.65" y="641.72" angle="0.00" type="DEFAULT_VEHTYPE" speed="46.95" pos="48.97" lane="4/6to4/7_0" slope="0.00"/>
        <vehicle id="8" x="491.65" y="654.63" angle="0.00" type="DEFAULT_VEHTYPE" speed="31.64" pos="61.88" lane="5/6to5/7_0" slope="0.00"/>
        <vehicle id="9" x="390.35" y="805.97" angle="180.00" type="DEFAULT_VEHTYPE" speed="20.58" pos="71.28" lane="4/9to4/8_0" slope="0.00"/>
    </timestep>
    <timestep time="24.00">
        <vehicle id="1" x="603.33" y="197.65" angle="270.00" type="DEFAULT_VEHTYPE" speed="16.05" pos="77.92" lane="7/2to6/2_0" slope="0.00"/>
        <vehicle id="10" x="194.35" y="162.11" angle="180.00" type="DEFAULT_VEHTYPE" speed="41.72" pos="29.14" lane="2/2to2/1_0" slope="0.00"/>
        <vehicle id="11" x="783.48" y="684.35" angle="90.00" type="DEFAULT_VEHTYPE" speed="22.45" pos="4.23" lane=":8/7_13_0" slope="0.00"/>
        <vehicle id="12" x="197.65" y="276.74" angle="0.00" type="DEFAULT_VEHTYPE" speed="22.94" pos="75.99" lane="2/2to2/3_0" slope="0.00"/>
        <vehicle id="13" x="99.65" y="597.44" angle="359.51" type="DEFAULT_VEHTYPE" speed="20.70" pos="4.69" lane="1/6to1/7_0" slope="0.00"/>
        <vehicle id="14" x="515.66" y="295.65" angle="270.00" type="DEFAULT_VEHTYPE" speed="19.77" pos="67.59" lane="6/3to5/3_0" slope="0.00"/>
        <vehicle id="15" x="1.65" y="500.83" angle="0.00" type="DEFAULT_VEHTYPE" speed="36.57" pos="6.08" lane="0/5to0/6_0" slope="0.00"/>
        <vehicle id="17" x="663.03" y="589.65" angle="270.00" type="DEFAULT_VEHTYPE" speed="8.18" pos="18.22" lane="7/6to6/6_0" slope="0.00"/>
        <vehicle id="18" x="981.65" y="190.01" angle="0.00" type="DEFAULT_VEHTYPE" speed="27.62" pos="87.26" lane="10/1to10/2_0" slope="0.00"/>
        <vehicle id="19" x="782.35" y="897.70" angle="180.00" type="DEFAULT_VEHTYPE" speed="25.04" pos="77.55" lane="8/10to8/9_0" slope="0.00"/>
        <vehicle id="2" x="414.44" y="295.65" angle="270.00" type="DEFAULT_VEHTYPE" speed="27.55" pos="70.81" lane="5/3to4/3_0" slope="0.00"/>
        <vehicle id="20" x="782.35" y="951.90" angle="180.00" type="DEFAULT_VEHTYPE" speed="19.53" pos="23.35" lane="8/10to8/9_0" slope="0.00"/>
        <vehicle id="21" x="291.43" y="393.65" angle="270.00" type="DEFAULT_VEHTYPE" speed="17.78" pos="7.32" lane=":3/4_5_0" slope="0.00"/>
        <vehicle id="22" x="384.01" y="295.65" angle="270.00" type="DEFAULT_VEHTYPE" speed="13.82" pos="3.24" lane="4/3to3/3_0" slope="0.00"/>
        <vehicle id="23" x="684.35" y="668.50" angle="180.00" type="DEFAULT_VEHTYPE" speed="6.56" pos="12.75" lane="7/7to7/6_0" slope="0.00"/>
        <vehicle id="24" x="13.30" y="491.65" angle="270.00" type="DEFAULT_VEHTYPE" speed="2.85" pos="79.95" lane="1/5to0/5_0" slope="0.00"/>
        <vehicle id="25" x="978.35" y="78.17" angle="180.00" type="DEFAULT_VEHTYPE" speed="50.00" pos="15.08" lane="10/1to10/0_0" slope="0.00"/>
        <vehicle id="26" x="231.36" y="194.35" angle="90.00" type="DEFAULT_VEHTYPE" speed="24.60" pos="30.61" lane="2/2to3/2_0" slope="0.00"/>
        <vehicle id="3" x="687.65" y="510.39" angle="0.00" type="DEFAULT_VEHTYPE" speed="42.75" pos="15.64" lane="7/5to7/6_0" slope="0.00"/>
        <vehicle id="6" x="284.91" y="684.35" angle="90.00" type="DEFAULT_VEHTYPE" speed="31.73" pos="84.16" lane="2/7to3/7_0" slope="0.00"/>
        <vehicle id="7" x="393.65" y="790.52" angle="0.00" type="DEFAULT_VEHTYPE" speed="49.60" pos="1.77" lane="4/8to4/9_0" slope="0.00"/>
        <vehicle id="8" x="491.65" y="767.92" angle="0.00" type="DEFAULT_VEHTYPE" speed="37.76" pos="77.17" lane="5/7to5/8_0" slope="0.00"/>
        <vehicle id="9" x="390.35" y="730.73" angle="180.00" type="DEFAULT_VEHTYPE" speed="25.08" pos="48.52" lane="4/8to4/7_0" slope="0.00"/>
    </timestep>
    <timestep time="27.00">
        <vehicle id="1" x="595.67" y="197.65" angle="270.00" type="DEFAULT_VEHTYPE" speed="2.55" pos="85.58" lane="7/2to6/2_0" slope="0.00"/>
        <vehicle id="10" x="194.35" y="54.31" angle="180.00" type="DEFAULT_VEHTYPE" speed="35.94" pos="38.94" lane="2/1to2/0_0" slope="0.00"/>
        <vehicle id="11" x="872.91" y="684.35" angle="90.00" type="DEFAULT_VEHTYPE" speed="29.81" pos="84.16" lane="8/7to9/7_0" slope="0.00"/>
        <vehicle id="12" x="197.65" y="363.45" angle="0.00" type="DEFAULT_VEHTYPE" speed="28.90" pos="64.70" lane="2/3to2/4_0" slope="0.00"/>
        <vehicle id="13" x="99.65" y="677.25" angle="0.00" type="DEFAULT_VEHTYPE" speed="26.60" pos="84.50" lane="1/6to1/7_0" slope="0.00"/>
        <vehicle id="14" x="479.01" y="295.65" angle="270.00" type="DEFAULT_VEHTYPE" speed="12.21" pos="6.24" lane="5/3to4/3_0" slope="0.00"/>
        <vehicle id="15" x="1.65" y="622.97" angle="0.00" type="DEFAULT_VEHTYPE" speed="40.71" pos="30.22" lane="0/6to0/7_0" slope="0.00"/>
        <vehicle id="17" x="625.74" y="589.65" angle="270.00" type="DEFAULT_VEHTYPE" speed="12.43" pos="55.51" lane="7/6to6/6_0" slope="0.00"/>
        <vehicle id="19" x="782.35" y="799.19" angle="180.00" type="DEFAULT_VEHTYPE" speed="32.83" pos="78.06" lane="8/9to8/8_0" slope="0.00"/>
        <vehicle id="2" x="372.30" y="295.65" angle="270.00" type="DEFAULT_VEHTYPE" speed="14.05" pos="14.95" lane="4/3to3/3_0" slope="0.00"/>
        <vehicle id="20" x="782.35" y="877.60" angle="180.00" type="DEFAULT_VEHTYPE" speed="24.77" pos="9.15" lane=":8/9_1_0" slope="0.00"/>
        <vehicle id="21" x="223.87" y="393.65" angle="270.00" type="DEFAULT_VEHTYPE" speed="22.52" pos="65.38" lane="3/4to2/4_0" slope="0.00"/>
        <vehicle id="22" x="324.56" y="295.65" angle="270.00" type="DEFAULT_VEHTYPE" speed="19.82" pos="62.69" lane="4/3to3/3_0" slope="0.00"/>
        <vehicle id="23" x="684.35" y="635.29" angle="180.00" type="DEFAULT_VEHTYPE" speed="11.07" pos="45.96" lane="7/7to7/6_0" slope="0.00"/>
        <vehicle id="24" x="8.75" y="491.65" angle="270.00" type="DEFAULT_VEHTYPE" speed="1.52" pos="84.50" lane="1/5to0/5_0" slope="0.00"/>
        <vehicle id="25" x="906.68" y="1.65" angle="270.00" type="DEFAULT_VEHTYPE" speed="49.19" pos="70.07" lane="10/0to9/0_0" slope="0.00"/>
        <vehicle id="26" x="295.65" y="204.46" angle="2.09" type="DEFAULT_VEHTYPE" speed="23.98" pos="3.71" lane="3/2to3/3_0" slope="0.00"/>
        <vehicle id="27" x="240.27" y="292.35" angle="90.00" type="DEFAULT_VEHTYPE" speed="22.37" pos="39.52" lane="2/3to3/3_0" slope="0.00"/>
        <vehicle id="28" x="96.35" y="554.63" angle="180.00" type="DEFAULT_VEHTYPE" speed="50.00" pos="28.62" lane="1/6to1/5_0" slope="0.00"/>
        <vehicle id="29" x="68.75" y="292.35" angle="90.00" type="DEFAULT_VEHTYPE" speed="16.25" pos="64.00" lane="0/3to1/3_0" slope="0.00"/>
        <vehicle id="3" x="687.65" y="650.43" angle="0.00" type="DEFAULT_VEHTYPE" speed="46.68" pos="57.68" lane="7/6to7/7_0" slope="0.00"/>
        <vehicle id="6" x="371.21" y="684.35" angle="90.00" type="DEFAULT_VEHTYPE" speed="28.77" pos="72.46" lane="3/7to4/7_0" slope="0.00"/>
        <vehicle id="7" x="393.65" y="914.20" angle="0.00" type="DEFAULT_VEHTYPE" speed="41.23" pos="27.45" lane="4/9to4/10_0" slope="0.00"/>
        <vehicle id="8" x="570.56" y="782.35" angle="90.00" type="DEFAULT_VEHTYPE" speed="30.71" pos="75.81" lane="5/8to6/8_0" slope="0.00"/>
        <vehicle id="9" x="390.35" y="632.23" angle="180.00" type="DEFAULT_VEHTYPE" speed="32.83" pos="49.02" lane="4/7to4/6_0" slope="0.00"/>
    </timestep>
    <timestep time="30.00">
        <vehicle id="1" x="569.81" y="197.65" angle="270.00" type="DEFAULT_VEHTYPE" speed="8.62" pos="13.44" lane="6/2to5/2_0" slope="0.00"/>
        <vehicle id="10" x="197.65" y="17.68" angle="0.00" type="DEFAULT_VEHTYPE" speed="22.44" pos="12.93" lane="2/0to2/1_0" slope="0.00"/>
        <vehicle id="11" x="965.04" y="684.35" angle="90.00" type="DEFAULT_VEHTYPE" speed="30.71" pos="78.29" lane="9/7to10/7_0" slope="0.00"/>
        <vehicle id="12" x="197.65" y="472.42" angle="0.00" type="DEFAULT_VEHTYPE" speed="36.32" pos="75.67" lane="2/4to2/5_0" slope="0.00"/>
        <vehicle id="13" x="99.65" y="771.08" angle="0.00" type="DEFAULT_VEHTYPE" speed="31.28" pos="80.33" lane="1/7to1/8_0" slope="0.00"/>
        <vehicle id="14" x="420.31" y="295.65" angle="270.00" type="DEFAULT_VEHTYPE" speed="19.57" pos="64.94" lane="5/3to4/3_0" slope="0.00"/>
        <vehicle id="15" x="1.65" y="765.72" angle="0.00" type="DEFAULT_VEHTYPE" speed="47.58" pos="74.97" lane="0/7to0/8_0" slope="0.00"/>
        <vehicle id="17" x="574.99" y="589.65" angle="270.00" type="DEFAULT_VEHTYPE" speed="16.92" pos="8.26" lane="6/6to5/6_0" slope="0.00"/>
        <vehicle id="19" x="782.35" y="679.94" angle="180.00" type="DEFAULT_VEHTYPE" speed="39.75" pos="1.31" lane="8/7to8/6_0" slope="0.00"/>
        <vehicle id="2" x="313.54" y="295.65" angle="270.00" type="DEFAULT_VEHTYPE" speed="19.59" pos="73.71" lane="4/3to3/3_0" slope="0.00"/>
        <vehicle id="20" x="782.35" y="782.57" angle="180.00" type="DEFAULT_VEHTYPE" speed="31.68" pos="6.18" lane=":8/8_1_0" slope="0.00"/>
        <vehicle id="21" x="197.65" y="405.26" angle="0.00" type="DEFAULT_VEHTYPE" speed="12.21" pos="8.51" lane="2/4to2/5_0" slope="0.00"/>
        <vehicle id="22" x="276.75" y="295.65" angle="270.00" type="DEFAULT_VEHTYPE" speed="15.94" pos="12.50" lane="3/3to2/3_0" slope="0.00"/>
        <vehicle id="23" x="684.35" y="580.20" angle="180.00" type="DEFAULT_VEHTYPE" speed="18.36" pos="3.05" lane="7/6to7/5_0" slope="0.00"/>
        <vehicle id="24" x="1.65" y="504.47" angle="0.00" type="DEFAULT_VEHTYPE" speed="6.24" pos="9.72" lane="0/5to0/6_0" slope="0.00"/>
        <vehicle id="25" x="759.26" y="1.65" angle="270.00" type="DEFAULT_VEHTYPE" speed="49.14" pos="19.99" lane="8/0to7/0_0" slope="0.00"/>
        <vehicle id="26" x="295.65" y="289.05" angle="0.00" type="DEFAULT_VEHTYPE" speed="28.19" pos="88.30" lane="3/2to3/3_0" slope="0.00"/>
        <vehicle id="27" x="295.65" y="301.76" angle="3.23" type="DEFAULT_VEHTYPE" speed="20.77" pos="3.01" lane="3/3to3/4_0" slope="0.00"/>
        <vehicle id="28" x="96.35" y="413.90" angle="180.00" type="DEFAULT_VEHTYPE" speed="46.91" pos="71.35" lane="1/5to1/4_0" slope="0.00"/>
        <vehicle id="29" x="99.65" y="305.95" angle="0.00" type="DEFAULT_VEHTYPE" speed="14.01" pos="7.20" lane="1/3to1/4_0" slope="0.00"/>
        <vehicle id="3" x="693.56" y="782.35" angle="82.83" type="DEFAULT_VEHTYPE" speed="45.54" pos="2.81" lane="7/8to8/8_0" slope="0.00"/>
        <vehicle id="30" x="589.65" y="306.24" angle="0.00" type="DEFAULT_VEHTYPE" speed="28.93" pos="7.49" lane="6/3to6/4_0" slope="0.00"/>
        <vehicle id="31" x="978.35" y="41.99" angle="180.00" type="DEFAULT_VEHTYPE" speed="50.00" pos="51.26" lane="10/1to10/0_0" slope="0.00"/>
        <vehicle id="32" x="286.19" y="883.65" angle="270.00" type="DEFAULT_VEHTYPE" speed="29.56" pos="3.06" lane="3/9to2/9_0" slope="0.00"/>
        <vehicle id="6" x="417.01" y="684.35" angle="90.00" type="DEFAULT_VEHTYPE" speed="15.27" pos="20.26" lane="4/7to5/7_0" slope="0.00"/>
        <vehicle id="7" x="413.89" y="978.35" angle="90.00" type="DEFAULT_VEHTYPE" speed="27.73" pos="17.14" lane="4/10to5/10_0" slope="0.00"/>
        <vehicle id="8" x="622.19" y="782.35" angle="90.00" type="DEFAULT_VEHTYPE" speed="17.21" pos="29.44" lane="6/8to7/8_0" slope="0.00"/>
        <vehicle id="9" x="390.35" y="512.61" angle="180.00" type="DEFAULT_VEHTYPE" speed="39.87" pos="70.64" lane="4/6to4/5_0" slope="0.00"/>
    </timestep>
    <timestep time="33.00">
        <vehicle id="1" x="521.94" y="197.65" angle="270.00" type="DEFAULT_VEHTYPE" speed="15.96" pos="61.31" lane="6/2to5/2_0" slope="0.00"/>
        <vehicle id="11" x="978.35" y="644.82" angle="180.00" type="DEFAULT_VEHTYPE" speed="17.21" pos="36.43" lane="10/7to10/6_0" slope="0.00"/>
        <vehicle id="12" x="197.65" y="595.51" angle="0.00" type="DEFAULT_VEHTYPE" speed="41.03" pos="2.76" lane="2/6to2/7_0" slope="0.00"/>
        <vehicle id="13" x="99.65" y="888.22" angle="0.00" type="DEFAULT_VEHTYPE" speed="39.05" pos="1.47" lane="1/9to1/10_0" slope="0.00"/>
        <vehicle id="14" x="393.65" y="309.49" angle="0.00" type="DEFAULT_VEHTYPE" speed="13.10" pos="10.74" lane="4/3to4/4_0" slope="0.00"/>
        <vehicle id="15" x="88.48" y="782.35" angle="90.00" type="DEFAULT_VEHTYPE" speed="34.08" pos="83.73" lane="0/8to1/8_0" slope="0.00"/>
        <vehicle id="17" x="506.17" y="589.65" angle="270.00" type="DEFAULT_VEHTYPE" speed="22.94" pos="77.08" lane="6/6to5/6_0" slope="0.00"/>
        <vehicle id="19" x="782.35" y="595.35" angle="180.00" type="DEFAULT_VEHTYPE" speed="28.19" pos="85.90" lane="8/7to8/6_0" slope="0.00"/>
        <vehicle id="2" x="295.65" y="311.58" angle="0.00" type="DEFAULT_VEHTYPE" speed="10.87" pos="12.83" lane="3/3to3/4_0" slope="0.00"/>
        <vehicle id="20" x="782.35" y="666.37" angle="180.00" type="DEFAULT_VEHTYPE" speed="38.73" pos="14.88" lane="8/7to8/6_0" slope="0.00"/>
        <vehicle id="21" x="197.65" y="456.65" angle="0.00" type="DEFAULT_VEHTYPE" speed="17.13" pos="59.90" lane="2/4to2/5_0" slope="0.00"/>
        <vehicle id="22" x="212.42" y="295.65" angle="270.00" type="DEFAULT_VEHTYPE" speed="21.44" pos="76.83" lane="3/3to2/3_0" slope="0.00"/>
        <vehicle id="23" x="684.35" y="502.70" angle="180.00" type="DEFAULT_VEHTYPE" speed="25.83" pos="80.55" lane="7/6to7/5_0" slope="0.00"/>
        <vehicle id="24" x="1.65" y="541.56" angle="0.00" type="DEFAULT_VEHTYPE" speed="12.36" pos="46.81" lane="0/5to0/6_0" slope="0.00"/>
        <vehicle id="25" x="620.29" y="1.65" angle="270.00" type="DEFAULT_VEHTYPE" speed="46.33" pos="60.96" lane="7/0to6/0_0" slope="0.00"/>
        <vehicle id="26" x="295.65" y="333.13" angle="0.00" type="DEFAULT_VEHTYPE" speed="14.69" pos="34.38" lane="3/3to3/4_0" slope="0.00"/>
        <vehicle id="27" x="295.65" y="376.77" angle="0.00" type="DEFAULT_VEHTYPE" speed="25.00" pos="78.02" lane="3/3to3/4_0" slope="0.00"/>
        <vehicle id="28" x="96.35" y="278.10" angle="180.00" type="DEFAULT_VEHTYPE" speed="45.27" pos="11.15" lane="1/3to1/2_0" slope="0.00"/>
        <vehicle id="29" x="99.65" y="360.79" angle="0.00" type="DEFAULT_VEHTYPE" speed="18.28" pos="62.04" lane="1/3to1/4_0" slope="0.00"/>
        <vehicle id="3" x="782.35" y="773.80" angle="180.00" type="DEFAULT_VEHTYPE" speed="32.04" pos="5.45" lane="8/8to8/7_0" slope="0.00"/>
        <vehicle id="30" x="588.68" y="391.00" angle="348.59" type="DEFAULT_VEHTYPE" speed="28.32" pos="3.94" lane=":6/4_10_0" slope="0.00"/>
        <vehicle id="31" x="870.77" y="1.65" angle="270.00" type="DEFAULT_VEHTYPE" speed="49.10" pos="6.48" lane="9/0to8/0_0" slope="0.00"/>
        <vehicle id="32" x="199.75" y="883.51" angle="268.36" type="DEFAULT_VEHTYPE" speed="28.81" pos="1.01" lane=":2/9_6_0" slope="0.00"/>
        <vehicle id="33" x="28.14" y="488.35" angle="90.00" type="DEFAULT_VEHTYPE" speed="26.40" pos="23.39" lane="0/5to1/5_0" slope="0.00"/>
        <vehicle id="34" x="491.65" y="44.31" angle="0.00" type="DEFAULT_VEHTYPE" speed="37.71" pos="39.56" lane="5/0to5/1_0" slope="0.00"/>
        <vehicle id="35" x="981.65" y="30.46" angle="0.00" type="DEFAULT_VEHTYPE" speed="25.82" pos="27.21" lane="10/0to10/1_0" slope="0.00"/>
        <vehicle id="6" x="486.08" y="684.35" angle="90.00" type="DEFAULT_VEHTYPE" speed="23.02" pos="0.83" lane=":5/7_13_0" slope="0.00"/>
        <vehicle id="7" x="513.70" y="978.35" angle="90.00" type="DEFAULT_VEHTYPE" speed="33.27" pos="18.95" lane="5/10to6/10_0" slope="0.00"/>
        <vehicle id="8" x="692.17" y="782.35" angle="90.00" type="DEFAULT_VEHTYPE" speed="23.33" pos="1.42" lane="7/8to8/8_0" slope="0.00"/>
        <vehicle id="9" x="390.35" y="381.08" angle="180.00" type="DEFAULT_VEHTYPE" speed="43.84" pos="6.17" lane="4/4to4/3_0" slope="0.00"/>
    </timestep>
    <timestep time="36.00">
        <vehicle id="1" x="480.15" y="197.65" angle="270.00" type="DEFAULT_VEHTYPE" speed="13.93" pos="5.10" lane="5/2to4/2_0" slope="0.00"/>
        <vehicle id="11" x="978.35" y="576.16" angle="180.00" type="DEFAULT_VEHTYPE" speed="22.89" pos="7.09" lane="10/6to10/5_0" slope="0.00"/>
        <vehicle id="12" x="197.65" y="738.67" angle="0.00" type="DEFAULT_VEHTYPE" speed="47.72" pos="47.92" lane="2/7to2/8_0" slope="0.00"/>
        <vehicle id="14" x="393.65" y="369.83" angle="0.00" type="DEFAULT_VEHTYPE" speed="20.11" pos="71.08" lane="4/3to4/4_0" slope="0.00"/>
        <vehicle id="15" x="150.23" y="782.35" angle="90.00" type="DEFAULT_VEHTYPE" speed="20.58" pos="47.48" lane="1/8to2/8_0" slope="0.00"/>
        <vehicle id="17" x="477.84" y="589.65" angle="270.00" type="DEFAULT_VEHTYPE" speed="9.44" pos="7.41" lane="5/6to4/6_0" slope="0.00"/>
        <vehicle id="19" x="819.91" y="586.35" angle="90.00" type="DEFAULT_VEHTYPE" speed="14.69" pos="31.16" lane="8/6to9/6_0" slope="0.00"/>
        <vehicle id="2" x="295.65" y="344.44" angle="0.00" type="DEFAULT_VEHTYPE" speed="10.95" pos="45.69" lane="3/3to3/4_0" slope="0.00"/>
        <vehicle id="20" x="782.35" y="573.38" angle="180.00" type="DEFAULT_VEHTYPE" speed="31.00" pos="9.87" lane="8/6to8/5_0" slope="0.00"/>
        <vehicle id="21" x="197.65" y="531.28" angle="0.00" type="DEFAULT_VEHTYPE" speed="24.88" pos="36.53" lane="2/5to2/6_0" slope="0.00"/>
        <vehicle id="22" x="188.59" y="295.65" angle="270.00" type="DEFAULT_VEHTYPE" speed="7.94" pos="2.66" lane="2/3to1/3_0" slope="0.00"/>
        <vehicle id="23" x="709.48" y="488.35" angle="90.00" type="DEFAULT_VEHTYPE" speed="12.33" pos="18.73" lane="7/5to8/5_0" slope="0.00"/>
        <vehicle id="24" x="14.27" y="586.35" angle="90.00" type="DEFAULT_VEHTYPE" speed="18.74" pos="9.52" lane="0/6to1/6_0" slope="0.00"/>
        <vehicle id="25" x="479.60" y="1.65" angle="270.00" type="DEFAULT_VEHTYPE" speed="46.89" pos="5.65" lane="5/0to4/0_0" slope="0.00"/>
        <vehicle id="26" x="286.57" y="393.65" angle="273.78" type="DEFAULT_VEHTYPE" speed="22.37" pos="2.68" lane="3/4to2/4_0" slope="0.00"/>
        <vehicle id="27" x="295.65" y="474.80" angle="0.00" type="DEFAULT_VEHTYPE" speed="32.68" pos="78.05" lane="3/4to3/5_0" slope="0.00"/>
        <vehicle id="28" x="110.38" y="194.35" angle="90.00" type="DEFAULT_VEHTYPE" speed="31.77" pos="7.63" lane="1/2to2/2_0" slope="0.00"/>
        <vehicle id="29" x="99.65" y="438.45" angle="0.00" type="DEFAULT_VEHTYPE" speed="25.89" pos="41.70" lane="1/4to1/5_0" slope="0.00"/>
        <vehicle id="30" x="507.33" y="393.65" angle="270.00" type="DEFAULT_VEHTYPE" speed="27.43" pos="75.92" lane="6/4to5/4_0" slope="0.00"/>
        <vehicle id="31" x="725.27" y="1.65" angle="270.00" type="DEFAULT_VEHTYPE" speed="48.50" pos="53.98" lane="8/0to7/0_0" slope="0.00"/>
        <vehicle id="32" x="194.35" y="780.71" angle="180.00" type="DEFAULT_VEHTYPE" speed="35.28" pos="8.04" lane=":2/8_1_0" slope="0.00"/>
        <vehicle id="33" x="99.65" y="495.02" angle="16.36" type="DEFAULT_VEHTYPE" speed="25.23" pos="0.27" lane="1/5to1/6_0" slope="0.00"/>
        <vehicle id="34" x="551.35" y="96.35" angle="90.00" type="DEFAULT_VEHTYPE" speed="36.85" pos="56.60" lane="5/1to6/1_0" slope="0.00"/>
        <vehicle id="35" x="968.95" y="99.65" angle="270.00" type="DEFAULT_VEHTYPE" speed="26.47" pos="6.30" lane="10/1to9/1_0" slope="0.00"/>
        <vehicle id="36" x="194.35" y="359.01" angle="180.00" type="DEFAULT_VEHTYPE" speed="25.19" pos="28.24" lane="2/4to2/3_0" slope="0.00"/>
        <vehicle id="6" x="572.61" y="684.35" angle="90.00" type="DEFAULT_VEHTYPE" speed="28.84" pos="77.86" lane="5/7to6/7_0" slope="0.00"/>
        <vehicle id="7" x="631.34" y="978.35" angle="90.00" type="DEFAULT_VEHTYPE" speed="39.21" pos="38.59" lane="6/10to7/10_0" slope="0.00"/>
        <vehicle id="8" x="772.22" y="782.35" angle="90.00" type="DEFAULT_VEHTYPE" speed="26.68" pos="81.47" lane="7/8to8/8_0" slope="0.00"/>
        <vehicle id="9" x="390.35" y="231.55" angle="180.00" type="DEFAULT_VEHTYPE" speed="49.85" pos="57.70" lane="4/3to4/2_0" slope="0.00"/>
    </timestep>
    <timestep time="39.00">
        <vehicle id="1" x="424.30" y="197.65" angle="270.00" type="DEFAULT_VEHTYPE" speed="18.62" pos="60.95" lane="5/2to4/2_0" slope="0.00"/>
        <vehicle id="11" x="978.35" y="488.86" angle="180.00" type="DEFAULT_VEHTYPE" speed="29.10" pos="5.89" lane=":10/5_1_0" slope="0.00"/>
        <vehicle id="12" x="257.83" y="782.35" angle="90.00" type="DEFAULT_VEHTYPE" speed="34.22" pos="57.08" lane="2/8to3/8_0" slope="0.00"/>
        <vehicle id="14" x="393.65" y="444.50" angle="0.00" type="DEFAULT_VEHTYPE" speed="24.89" pos="47.75" lane="4/4to4/5_0" slope="0.00"/>
        <vehicle id="15" x="194.35" y="775.37" angle="178.22" type="DEFAULT_VEHTYPE" speed="16.63" pos="3.88" lane="2/8to2/7_0" slope="0.00"/>
        <vehicle id="17" x="426.44" y="589.65" angle="270.00" type="DEFAULT_VEHTYPE" speed="17.14" pos="58.81" lane="5/6to4/6_0" slope="0.00"/>
        <vehicle id="19" x="880.20" y="584.29" angle="117.20" type="DEFAULT_VEHTYPE" speed="20.43" pos="3.95" lane=":9/6_12_0" slope="0.00"/>
        <vehicle id="2" x="295.65" y="389.94" angle="0.00" type="DEFAULT_VEHTYPE" speed="15.17" pos="2.69" lane=":3/4_9_0" slope="0.00"/>
        <vehicle id="20" x="782.35" y="466.86" angle="180.00" type="DEFAULT_VEHTYPE" speed="35.51" pos="18.39" lane="8/5to8/4_0" slope="0.00"/>
        <vehicle id="21" x="197.65" y="627.16" angle="0.00" type="DEFAULT_VEHTYPE" speed="31.96" pos="34.41" lane="2/6to2/7_0" slope="0.00"/>
        <vehicle id="22" x="148.11" y="295.65" angle="270.00" type="DEFAULT_VEHTYPE" speed="13.49" pos="43.14" lane="2/3to1/3_0" slope="0.00"/>
        <vehicle id="23" x="764.40" y="488.35" angle="90.00" type="DEFAULT_VEHTYPE" speed="18.31" pos="73.65" lane="7/5to8/5_0" slope="0.00"/>
        <vehicle id="24" x="89.24" y="586.35" angle="90.00" type="DEFAULT_VEHTYPE" speed="24.99" pos="84.49" lane="0/6to1/6_0" slope="0.00"/>
        <vehicle id="25" x="393.65" y="58.78" angle="0.00" type="DEFAULT_VEHTYPE" speed="47.30" pos="54.03" lane="4/0to4/1_0" slope="0.00"/>
        <vehicle id="27" x="295.65" y="585.41" angle="0.00" type="DEFAULT_VEHTYPE" speed="36.87" pos="2.16" lane=":3/6_9_0" slope="0.00"/>
        <vehicle id="28" x="190.39" y="194.35" angle="90.00" type="DEFAULT_VEHTYPE" speed="26.67" pos="87.64" lane="1/2to2/2_0" slope="0.00"/>
        <vehicle id="29" x="99.65" y="519.03" angle="0.00" type="DEFAULT_VEHTYPE" speed="26.86" pos="24.28" lane="1/5to1/6_0" slope="0.00"/>
        <vehicle id="30" x="465.52" y="393.65" angle="270.00" type="DEFAULT_VEHTYPE" speed="13.93" pos="19.73" lane="5/4to4/4_0" slope="0.00"/>
        <vehicle id="31" x="589.65" y="13.39" angle="0.00" type="DEFAULT_VEHTYPE" speed="48.72" pos="8.64" lane="6/0to6/1_0" slope="0.00"/>
        <vehicle id="32" x="194.35" y="662.86" angle="180.00" type="DEFAULT_VEHTYPE" speed="39.28" pos="18.39" lane="2/7to2/6_0" slope="0.00"/>
        <vehicle id="33" x="99.65" y="584.87" angle="0.00" type="DEFAULT_VEHTYPE" speed="29.95" pos="1.62" lane=":1/6_9_0" slope="0.00"/>
        <vehicle id="34" x="621.40" y="96.35" angle="90.00" type="DEFAULT_VEHTYPE" speed="23.35" pos="28.65" lane="6/1to7/1_0" slope="0.00"/>
        <vehicle id="35" x="888.77" y="99.65" angle="270.00" type="DEFAULT_VEHTYPE" speed="26.73" pos="86.48" lane="10/1to9/1_0" slope="0.00"/>
        <vehicle id="36" x="197.65" y="305.97" angle="0.00" type="DEFAULT_VEHTYPE" speed="24.10" pos="7.22" lane="2/3to2/4_0" slope="0.00"/>
        <vehicle id="37" x="383.50" y="194.35" angle="90.00" type="DEFAULT_VEHTYPE" speed="1.25" pos="84.75" lane="3/2to4/2_0" slope="0.00"/>
        <vehicle id="6" x="618.65" y="684.35" angle="90.00" type="DEFAULT_VEHTYPE" speed="15.34" pos="25.90" lane="6/7to7/7_0" slope="0.00"/>
        <vehicle id="7" x="761.83" y="978.35" angle="90.00" type="DEFAULT_VEHTYPE" speed="43.50" pos="71.08" lane="7/10to8/10_0" slope="0.00"/>
        <vehicle id="8" x="782.35" y="751.74" angle="180.00" type="DEFAULT_VEHTYPE" speed="13.18" pos="27.51" lane="8/8to8/7_0" slope="0.00"/>
        <vehicle id="9" x="390.35" y="96.56" angle="180.00" type="DEFAULT_VEHTYPE" speed="44.99" pos="6.19" lane=":4/1_1_0" slope="0.00"/>
    </timestep>
    <timestep time="42.00">
        <vehicle id="1" x="383.76" y="197.65" angle="270.00" type="DEFAULT_VEHTYPE" speed="13.51" pos="3.49" lane="4/2to3/2_0" slope="0.00"/>
        <vehicle id="11" x="978.35" y="380.73" angle="180.00" type="DEFAULT_VEHTYPE" speed="36.04" pos="6.52" lane="10/4to10/3_0" slope="0.00"/>
        <vehicle id="12" x="319.99" y="782.35" angle="90.00" type="DEFAULT_VEHTYPE" speed="20.72" pos="21.24" lane="3/8to4/8_0" slope="0.00"/>
        <vehicle id="14" x="393.65" y="540.90" angle="0.00" type="DEFAULT_VEHTYPE" speed="32.13" pos="46.15" lane="4/5to4/6_0" slope="0.00"/>
        <vehicle id="15" x="194.35" y="709.04" angle="180.00" type="DEFAULT_VEHTYPE" speed="22.11" pos="70.21" lane="2/8to2/7_0" slope="0.00"/>
        <vehicle id="17" x="377.63" y="589.65" angle="270.00" type="DEFAULT_VEHTYPE" speed="16.27" pos="9.62" lane="4/6to3/6_0" slope="0.00"/>
        <vehicle id="19" x="880.35" y="502.53" angle="180.00" type="DEFAULT_VEHTYPE" speed="27.26" pos="80.72" lane="9/6to9/5_0" slope="0.00"/>
        <vehicle id="2" x="295.65" y="448.84" angle="0.00" type="DEFAULT_VEHTYPE" speed="19.63" pos="52.09" lane="3/4to3/5_0" slope="0.00"/>
        <vehicle id="20" x="782.35" y="343.34" angle="180.00" type="DEFAULT_VEHTYPE" speed="41.17" pos="43.91" lane="8/4to8/3_0" slope="0.00"/>
        <vehicle id="21" x="197.65" y="745.70" angle="0.00" type="DEFAULT_VEHTYPE" speed="39.51" pos="54.95" lane="2/7to2/8_0" slope="0.00"/>
        <vehicle id="22" x="99.65" y="311.36" angle="0.00" type="DEFAULT_VEHTYPE" speed="20.99" pos="12.61" lane="1/3to1/4_0" slope="0.00"/>
        <vehicle id="23" x="795.86" y="488.35" angle="90.00" type="DEFAULT_VEHTYPE" speed="10.49" pos="7.11" lane="8/5to9/5_0" slope="0.00"/>
        <vehicle id="24" x="7.80" y="589.65" angle="270.00" type="DEFAULT_VEHTYPE" speed="31.43" pos="85.45" lane="1/6to0/6_0" slope="0.00"/>
        <vehicle id="25" x="393.65" y="165.56" angle="0.00" type="DEFAULT_VEHTYPE" speed="35.59" pos="62.81" lane="4/1to4/2_0" slope="0.00"/>
        <vehicle id="27" x="295.65" y="711.42" angle="0.00" type="DEFAULT_VEHTYPE" speed="42.01" pos="20.67" lane="3/7to3/8_0" slope="0.00"/>
        <vehicle id="28" x="284.70" y="194.35" angle="90.00" type="DEFAULT_VEHTYPE" speed="31.43" pos="83.95" lane="2/2to3/2_0" slope="0.00"/>
        <vehicle id="29" x="99.65" y="614.73" angle="0.00" type="DEFAULT_VEHTYPE" speed="31.90" pos="21.98" lane="1/6to1/7_0" slope="0.00"/>
        <vehicle id="30" x="409.86" y="393.65" angle="270.00" type="DEFAULT_VEHTYPE" speed="18.55" pos="75.39" lane="5/4to4/4_0" slope="0.00"/>
        <vehicle id="31" x="589.65" y="155.45" angle="0.00" type="DEFAULT_VEHTYPE" speed="47.35" pos="52.70" lane="6/1to6/2_0" slope="0.00"/>
        <vehicle id="32" x="194.35" y="526.07" angle="180.00" type="DEFAULT_VEHTYPE" speed="45.60" pos="57.18" lane="2/6to2/5_0" slope="0.00"/>
        <vehicle id="33" x="112.88" y="684.35" angle="90.00" type="DEFAULT_VEHTYPE" speed="37.17" pos="10.13" lane="1/7to2/7_0" slope="0.00"/>
        <vehicle id="34" x="693.38" y="96.35" angle="90.00" type="DEFAULT_VEHTYPE" speed="23.99" pos="2.63" lane="7/1to8/1_0" slope="0.00"/>
        <vehicle id="35" x="805.44" y="99.65" angle="270.00" type="DEFAULT_VEHTYPE" speed="27.77" pos="71.81" lane="9/1to8/1_0" slope="0.00"/>
        <vehicle id="36" x="197.65" y="395.67" angle="0.00" type="DEFAULT_VEHTYPE" speed="29.90" pos="8.42" lane=":2/4_9_0" slope="0.00"/>
        <vehicle id="37" x="369.99" y="197.65" angle="270.00" type="DEFAULT_VEHTYPE" speed="8.61" pos="17.26" lane="4/2to3/2_0" slope="0.00"/>
        <vehicle id="6" x="679.17" y="684.35" angle="90.00" type="DEFAULT_VEHTYPE" speed="20.17" pos="86.42" lane="6/7to7/7_0" slope="0.00"/>
        <vehicle id="9" x="392.23" y="3.22" angle="153.98" type="DEFAULT_VEHTYPE" speed="31.49" pos="2.67" lane=":4/0_2_0" slope="0.00"/>
    </timestep>
    <timestep time="45.00">
        <vehicle id="1" x="381.47" y="197.65" angle="270.00" type="DEFAULT_VEHTYPE" speed="0.76" pos="5.78" lane="4/2to3/2_0" slope="0.00"/>
        <vehicle id="11" x="978.35" y="256.27" angle="180.00" type="DEFAULT_VEHTYPE" speed="41.49" pos="32.98" lane="10/3to10/2_0" slope="0.00"/>
        <vehicle id="12" x="389.79" y="782.35" angle="90.00" type="DEFAULT_VEHTYPE" speed="23.27" pos="2.54" lane=":4/8_13_0" slope="0.00"/>
        <vehicle id="14" x="393.65" y="656.49" angle="0.00" type="DEFAULT_VEHTYPE" speed="38.53" pos="63.74" lane="4/6to4/7_0" slope="0.00"/>
        <vehicle id="17" x="315.97" y="589.65" angle="270.00" type="DEFAULT_VEHTYPE" speed="20.55" pos="71.28" lane="4/6to3/6_0" slope="0.00"/>
        <vehicle id="2" x="295.65" y="525.05" angle="0.00" type="DEFAULT_VEHTYPE" speed="25.40" pos="30.30" lane="3/5to3/6_0" slope="0.00"/>
        <vehicle id="20" x="785.65" y="332.36" angle="0.00" type="DEFAULT_VEHTYPE" speed="27.67" pos="33.61" lane="8/3to8/4_0" slope="0.00"/>
        <vehicle id="22" x="99.65" y="386.32" angle="0.00" type="DEFAULT_VEHTYPE" speed="24.99" pos="87.57" lane="1/3to1/4_0" slope="0.00"/>
        <vehicle id="23" x="850.02" y="488.35" angle="90.00" type="DEFAULT_VEHTYPE" speed="18.05" pos="61.27" lane="8/5to9/5_0" slope="0.00"/>
        <vehicle id="25" x="390.35" y="155.49" angle="180.00" type="DEFAULT_VEHTYPE" speed="22.09" pos="35.76" lane="4/2to4/1_0" slope="0.00"/>
        <vehicle id="27" x="295.65" y="858.17" angle="0.00" type="DEFAULT_VEHTYPE" speed="48.92" pos="69.42" lane="3/8to3/9_0" slope="0.00"/>
        <vehicle id="28" x="338.50" y="194.35" angle="90.00" type="DEFAULT_VEHTYPE" speed="17.93" pos="39.75" lane="3/2to4/2_0" slope="0.00"/>
        <vehicle id="29" x="99.65" y="731.06" angle="0.00" type="DEFAULT_VEHTYPE" speed="38.78" pos="40.31" lane="1/7to1/8_0" slope="0.00"/>
        <vehicle id="30" x="394.70" y="393.65" angle="270.00" type="DEFAULT_VEHTYPE" speed="5.05" pos="2.05" lane=":4/4_5_0" slope="0.00"/>
        <vehicle id="31" x="589.65" y="293.86" angle="0.00" type="DEFAULT_VEHTYPE" speed="46.14" pos="4.61" lane=":6/3_9_0" slope="0.00"/>
        <vehicle id="32" x="194.35" y="423.79" angle="180.00" type="DEFAULT_VEHTYPE" speed="34.09" pos="61.46" lane="2/5to2/4_0" slope="0.00"/>
        <vehicle id="33" x="192.44" y="684.35" angle="90.00" type="DEFAULT_VEHTYPE" speed="26.52" pos="1.19" lane=":2/7_13_0" slope="0.00"/>
        <vehicle id="34" x="775.00" y="96.35" angle="90.00" type="DEFAULT_VEHTYPE" speed="27.21" pos="84.25" lane="7/1to8/1_0" slope="0.00"/>
        <vehicle id="35" x="762.62" y="99.65" angle="270.00" type="DEFAULT_VEHTYPE" speed="14.27" pos="16.63" lane="8/1to7/1_0" slope="0.00"/>
        <vehicle id="36" x="197.65" y="508.71" angle="0.00" type="DEFAULT_VEHTYPE" speed="37.68" pos="13.96" lane="2/5to2/6_0" slope="0.00"/>
        <vehicle id="37" x="330.55" y="197.65" angle="270.00" type="DEFAULT_VEHTYPE" speed="13.15" pos="56.70" lane="4/2to3/2_0" slope="0.00"/>
        <vehicle id="6" x="762.11" y="684.35" angle="90.00" type="DEFAULT_VEHTYPE" speed="27.65" pos="71.36" lane="7/7to8/7_0" slope="0.00"/>
    </timestep>
    <timestep time="48.00">
        <vehicle id="1" x="365.97" y="197.65" angle="270.00" type="DEFAULT_VEHTYPE" speed="5.17" pos="21.28" lane="4/2to3/2_0" slope="0.00"/>
        <vehicle id="11" x="895.44" y="197.65" angle="270.00" type="DEFAULT_VEHTYPE" speed="46.78" pos="79.81" lane="10/2to9/2_0" slope="0.00"/>
        <vehicle id="12" x="471.87" y="782.35" angle="90.00" type="DEFAULT_VEHTYPE" speed="27.36" pos="75.12" lane="4/8to5/8_0" slope="0.00"/>
        <vehicle id="14" x="393.65" y="770.80" angle="0.00" type="DEFAULT_VEHTYPE" speed="38.10" pos="80.05" lane="4/7to4/8_0" slope="0.00"/>
        <vehicle id="17" x="281.33" y="589.65" angle="270.00" type="DEFAULT_VEHTYPE" speed="11.55" pos="7.92" lane="3/6to2/6_0" slope="0.00"/>
        <vehicle id="2" x="325.65" y="586.35" angle="90.00" type="DEFAULT_VEHTYPE" speed="30.04" pos="26.90" lane="3/6to4/6_0" slope="0.00"/>
        <vehicle id="22" x="99.65" y="480.84" angle="0.00" type="DEFAULT_VEHTYPE" speed="31.50" pos="84.09" lane="1/4to1/5_0" slope="0.00"/>
        <vehicle id="23" x="880.35" y="476.65" angle="180.00" type="DEFAULT_VEHTYPE" speed="13.61" pos="8.60" lane="9/5to9/4_0" slope="0.00"/>
        <vehicle id="27" x="380.92" y="880.35" angle="90.00" type="DEFAULT_VEHTYPE" speed="35.42" pos="82.17" lane="3/9to4/9_0" slope="0.00"/>
        <vehicle id="29" x="99.65" y="870.17" angle="0.00" type="DEFAULT_VEHTYPE" speed="46.37" pos="81.42" lane="1/8to1/9_0" slope="0.00"/>
        <vehicle id="30" x="356.31" y="393.65" angle="270.00" type="DEFAULT_VEHTYPE" speed="12.80" pos="30.94" lane="4/4to3/4_0" slope="0.00"/>
        <vehicle id="31" x="589.65" y="435.08" angle="0.00" type="DEFAULT_VEHTYPE" speed="47.07" pos="38.33" lane="6/4to6/5_0" slope="0.00"/>
        <vehicle id="32" x="225.17" y="390.35" angle="90.00" type="DEFAULT_VEHTYPE" speed="20.59" pos="24.42" lane="2/4to3/4_0" slope="0.00"/>
        <vehicle id="33" x="283.51" y="684.35" angle="90.00" type="DEFAULT_VEHTYPE" speed="30.36" pos="82.76" lane="2/7to3/7_0" slope="0.00"/>
        <vehicle id="34" x="744.27" y="99.65" angle="270.00" type="DEFAULT_VEHTYPE" speed="14.68" pos="34.98" lane="8/1to7/1_0" slope="0.00"/>
        <vehicle id="35" x="705.30" y="99.65" angle="270.00" type="DEFAULT_VEHTYPE" speed="19.11" pos="73.95" lane="8/1to7/1_0" slope="0.00"/>
        <vehicle id="36" x="197.65" y="632.63" angle="0.00" type="DEFAULT_VEHTYPE" speed="41.31" pos="39.88" lane="2/6to2/7_0" slope="0.00"/>
        <vehicle id="37" x="282.72" y="197.65" angle="270.00" type="DEFAULT_VEHTYPE" speed="15.94" pos="6.53" lane="3/2to2/2_0" slope="0.00"/>
        <vehicle id="6" x="804.56" y="684.35" angle="90.00" type="DEFAULT_VEHTYPE" speed="14.15" pos="15.81" lane="8/7to9/7_0" slope="0.00"/>
    </timestep>
    <timestep time="51.00">
        <vehicle id="1" x="336.58" y="197.65" angle="270.00" type="DEFAULT_VEHTYPE" speed="9.80" pos="50.67" lane="4/2to3/2_0" slope="0.00"/>
        <vehicle id="14" x="393.65" y="904.04" angle="0.00" type="DEFAULT_VEHTYPE" speed="44.41" pos="17.29" lane="4/9to4/10_0" slope="0.00"/>
        <vehicle id="17" x="229.41" y="589.65" angle="270.00" type="DEFAULT_VEHTYPE" speed="17.31" pos="59.84" lane="3/6to2/6_0" slope="0.00"/>
        <vehicle id="22" x="99.65" y="592.38" angle="0.00" type="DEFAULT_VEHTYPE" speed="37.18" pos="9.13" lane=":1/6_9_0" slope="0.00"/>
        <vehicle id="23" x="880.35" y="414.17" angle="180.00" type="DEFAULT_VEHTYPE" speed="20.82" pos="71.08" lane="9/5to9/4_0" slope="0.00"/>
        <vehicle id="27" x="446.67" y="880.35" angle="90.00" type="DEFAULT_VEHTYPE" speed="21.92" pos="49.92" lane="4/9to5/9_0" slope="0.00"/>
        <vehicle id="29" x="189.28" y="880.35" angle="90.00" type="DEFAULT_VEHTYPE" speed="32.87" pos="86.53" lane="1/9to2/9_0" slope="0.00"/>
        <vehicle id="30" x="301.02" y="393.65" angle="270.00" type="DEFAULT_VEHTYPE" speed="18.43" pos="86.23" lane="4/4to3/4_0" slope="0.00"/>
        <vehicle id="31" x="589.65" y="583.58" angle="0.00" type="DEFAULT_VEHTYPE" speed="49.50" pos="0.33" lane=":6/6_9_0" slope="0.00"/>
        <vehicle id="32" x="296.36" y="390.35" angle="90.00" type="DEFAULT_VEHTYPE" speed="23.73" pos="7.11" lane=":3/4_13_0" slope="0.00"/>
        <vehicle id="33" x="334.08" y="684.35" angle="90.00" type="DEFAULT_VEHTYPE" speed="16.86" pos="35.33" lane="3/7to4/7_0" slope="0.00"/>
        <vehicle id="35" x="669.05" y="99.65" angle="270.00" type="DEFAULT_VEHTYPE" speed="12.08" pos="12.20" lane="7/1to6/1_0" slope="0.00"/>
        <vehicle id="36" x="259.29" y="684.35" angle="90.00" type="DEFAULT_VEHTYPE" speed="37.39" pos="58.54" lane="2/7to3/7_0" slope="0.00"/>
        <vehicle id="37" x="217.57" y="197.65" angle="270.00" type="DEFAULT_VEHTYPE" speed="21.72" pos="71.68" lane="3/2to2/2_0" slope="0.00"/>
        <vehicle id="6" x="865.42" y="684.35" angle="90.00" type="DEFAULT_VEHTYPE" speed="20.29" pos="76.67" lane="8/7to9/7_0" slope="0.00"/>
    </timestep>
    <timestep time="54.00">
        <vehicle id="1" x="287.24" y="197.65" angle="270.00" type="DEFAULT_VEHTYPE" speed="16.44" pos="2.01" lane="3/2to2/2_0" slope="0.00"/>
        <vehicle id="14" x="390.35" y="958.54" angle="180.00" type="DEFAULT_VEHTYPE" speed="30.91" pos="16.71" lane="4/10to4/9_0" slope="0.00"/>
        <vehicle id="17" x="178.89" y="589.65" angle="270.00" type="DEFAULT_VEHTYPE" speed="16.84" pos="12.36" lane="2/6to1/6_0" slope="0.00"/>
        <vehicle id="22" x="99.65" y="710.86" angle="0.00" type="DEFAULT_VEHTYPE" speed="39.49" pos="20.11" lane="1/7to1/8_0" slope="0.00"/>
        <vehicle id="27" x="491.65" y="892.54" angle="0.00" type="DEFAULT_VEHTYPE" speed="18.23" pos="5.79" lane="5/9to5/10_0" slope="0.00"/>
        <vehicle id="29" x="273.23" y="880.35" angle="90.00" type="DEFAULT_VEHTYPE" speed="27.98" pos="72.48" lane="2/9to3/9_0" slope="0.00"/>
        <vehicle id="30" x="224.56" y="393.65" angle="270.00" type="DEFAULT_VEHTYPE" speed="25.49" pos="64.69" lane="3/4to2/4_0" slope="0.00"/>
        <vehicle id="31" x="589.65" y="725.22" angle="0.00" type="DEFAULT_VEHTYPE" speed="47.21" pos="34.47" lane="6/7to6/8_0" slope="0.00"/>
        <vehicle id="32" x="383.44" y="390.35" angle="90.00" type="DEFAULT_VEHTYPE" speed="29.03" pos="84.69" lane="3/4to4/4_0" slope="0.00"/>
        <vehicle id="33" x="392.58" y="686.83" angle="60.84" type="DEFAULT_VEHTYPE" speed="19.79" pos="6.19" lane=":4/7_14_0" slope="0.00"/>
        <vehicle id="35" x="612.28" y="99.65" angle="270.00" type="DEFAULT_VEHTYPE" speed="18.92" pos="68.97" lane="7/1to6/1_0" slope="0.00"/>
        <vehicle id="36" x="330.95" y="684.35" angle="90.00" type="DEFAULT_VEHTYPE" speed="23.89" pos="32.20" lane="3/7to4/7_0" slope="0.00"/>
        <vehicle id="37" x="197.65" y="212.36" angle="0.00" type="DEFAULT_VEHTYPE" speed="11.14" pos="11.61" lane="2/2to2/3_0" slope="0.00"/>
        <vehicle id="6" x="873.53" y="687.65" angle="278.39" type="DEFAULT_VEHTYPE" speed="6.79" pos="3.72" lane="9/7to8/7_0" slope="0.00"/>
    </timestep>
    <timestep time="57.00">
        <vehicle id="1" x="219.41" y="197.65" angle="270.00" type="DEFAULT_VEHTYPE" speed="22.61" pos="69.84" lane="3/2to2/2_0" slope="0.00"/>
        <vehicle id="17" x="111.55" y="589.65" angle="270.00" type="DEFAULT_VEHTYPE" speed="22.45" pos="79.70" lane="2/6to1/6_0" slope="0.00"/>
        <vehicle id="22" x="96.35" y="772.37" angle="180.00" type="DEFAULT_VEHTYPE" speed="26.70" pos="6.88" lane="1/8to1/7_0" slope="0.00"/>
        <vehicle id="27" x="491.65" y="965.67" angle="0.00" type="DEFAULT_VEHTYPE" speed="24.38" pos="78.92" lane="5/9to5/10_0" slope="0.00"/>
        <vehicle id="29" x="316.68" y="880.35" angle="90.00" type="DEFAULT_VEHTYPE" speed="14.48" pos="17.93" lane="3/9to4/9_0" slope="0.00"/>
        <vehicle id="30" x="197.65" y="415.14" angle="0.00" type="DEFAULT_VEHTYPE" speed="15.73" pos="18.39" lane="2/4to2/5_0" slope="0.00"/>
        <vehicle id="31" x="589.65" y="863.70" angle="0.00" type="DEFAULT_VEHTYPE" speed="46.16" pos="74.95" lane="6/8to6/9_0" slope="0.00"/>
        <vehicle id="32" x="476.37" y="390.35" angle="90.00" type="DEFAULT_VEHTYPE" speed="30.98" pos="79.62" lane="4/4to5/4_0" slope="0.00"/>
        <vehicle id="33" x="393.65" y="767.49" angle="0.00" type="DEFAULT_VEHTYPE" speed="26.95" pos="76.74" lane="4/7to4/8_0" slope="0.00"/>
        <vehicle id="35" x="575.15" y="99.65" angle="270.00" type="DEFAULT_VEHTYPE" speed="12.38" pos="8.10" lane="6/1to5/1_0" slope="0.00"/>
        <vehicle id="36" x="398.28" y="684.35" angle="90.00" type="DEFAULT_VEHTYPE" speed="22.44" pos="1.53" lane="4/7to5/7_0" slope="0.00"/>
        <vehicle id="37" x="197.65" y="258.40" angle="0.00" type="DEFAULT_VEHTYPE" speed="15.35" pos="57.65" lane="2/2to2/3_0" slope="0.00"/>
        <vehicle id="6" x="841.05" y="687.65" angle="270.00" type="DEFAULT_VEHTYPE" speed="10.83" pos="36.20" lane="9/7to8/7_0" slope="0.00"/>
    </timestep>
    <timestep time="60.00">
        <vehicle id="1" x="182.00" y="197.65" angle="270.00" type="DEFAULT_VEHTYPE" speed="12.47" pos="9.25" lane="2/2to1/2_0" slope="0.00"/>
        <vehicle id="17" x="96.35" y="575.53" angle="180.00" type="DEFAULT_VEHTYPE" speed="8.95" pos="7.72" lane="1/6to1/5_0" slope="0.00"/>
        <vehicle id="29" x="373.41" y="880.35" angle="90.00" type="DEFAULT_VEHTYPE" speed="18.91" pos="74.66" lane="3/9to4/9_0" slope="0.00"/>
        <vehicle id="30" x="197.65" y="479.63" angle="0.00" type="DEFAULT_VEHTYPE" speed="21.50" pos="82.88" lane="2/4to2/5_0" slope="0.00"/>
        <vehicle id="32" x="528.81" y="390.35" angle="90.00" type="DEFAULT_VEHTYPE" speed="17.48" pos="34.06" lane="5/4to6/4_0" slope="0.00"/>
        <vehicle id="35" x="521.56" y="99.65" angle="270.00" type="DEFAULT_VEHTYPE" speed="17.86" pos="61.69" lane="6/1to5/1_0" slope="0.00"/>
        <vehicle id="36" x="481.62" y="684.35" angle="90.00" type="DEFAULT_VEHTYPE" speed="27.78" pos="84.87" lane="4/7to5/7_0" slope="0.00"/>
        <vehicle id="37" x="197.65" y="324.22" angle="0.00" type="DEFAULT_VEHTYPE" speed="21.94" pos="25.47" lane="2/3to2/4_0" slope="0.00"/>
    </timestep>
    <timestep time="63.00">
        <vehicle id="1" x="128.15" y="197.65" angle="270.00" type="DEFAULT_VEHTYPE" speed="17.95" pos="63.10" lane="2/2to1/2_0" slope="0.00"/>
        <vehicle id="17" x="96.35" y="535.15" angle="180.00" type="DEFAULT_VEHTYPE" speed="13.46" pos="48.10" lane="1/6to1/5_0" slope="0.00"/>
        <vehicle id="29" x="404.35" y="880.35" angle="90.00" type="DEFAULT_VEHTYPE" speed="10.31" pos="7.60" lane="4/9to5/9_0" slope="0.00"/>
        <vehicle id="30" x="197.65" y="567.24" angle="0.00" type="DEFAULT_VEHTYPE" speed="29.21" pos="72.49" lane="2/5to2/6_0" slope="0.00"/>
        <vehicle id="32" x="586.35" y="378.75" angle="180.00" type="DEFAULT_VEHTYPE" speed="22.65" pos="8.50" lane="6/4to6/3_0" slope="0.00"/>
        <vehicle id="35" x="473.48" y="99.65" angle="270.00" type="DEFAULT_VEHTYPE" speed="16.03" pos="11.77" lane="5/1to4/1_0" slope="0.00"/>
        <vehicle id="36" x="571.23" y="684.35" angle="90.00" type="DEFAULT_VEHTYPE" speed="29.87" pos="76.48" lane="5/7to6/7_0" slope="0.00"/>
    </timestep>
    <timestep time="66.00">
        <vehicle id="1" x="81.00" y="197.65" angle="270.00" type="DEFAULT_VEHTYPE" speed="15.72" pos="12.25" lane="1/2to0/2_0" slope="0.00"/>
        <vehicle id="17" x="96.35" y="477.93" angle="180.00" type="DEFAULT_VEHTYPE" speed="19.07" pos="7.32" lane="1/5to1/4_0" slope="0.00"/>
        <vehicle id="29" x="450.60" y="880.35" angle="90.00" type="DEFAULT_VEHTYPE" speed="15.42" pos="53.85" lane="4/9to5/9_0" slope="0.00"/>
        <vehicle id="30" x="197.65" y="674.11" angle="0.00" type="DEFAULT_VEHTYPE" speed="35.62" pos="81.36" lane="2/6to2/7_0" slope="0.00"/>
        <vehicle id="35" x="409.48" y="99.65" angle="270.00" type="DEFAULT_VEHTYPE" speed="21.33" pos="75.77" lane="5/1to4/1_0" slope="0.00"/>
        <vehicle id="36" x="620.33" y="684.35" angle="90.00" type="DEFAULT_VEHTYPE" speed="16.37" pos="27.58" lane="6/7to7/7_0" slope="0.00"/>
    </timestep>
    <timestep time="69.00">
        <vehicle id="1" x="12.52" y="197.65" angle="270.00" type="DEFAULT_VEHTYPE" speed="22.82" pos="80.73" lane="1/2to0/2_0" slope="0.00"/>
        <vehicle id="17" x="96.35" y="406.90" angle="180.00" type="DEFAULT_VEHTYPE" speed="23.68" pos="78.35" lane="1/5to1/4_0" slope="0.00"/>
        <vehicle id="29" x="499.50" y="880.35" angle="90.00" type="DEFAULT_VEHTYPE" speed="16.30" pos="4.75" lane="5/9to6/9_0" slope="0.00"/>
        <vehicle id="30" x="197.65" y="794.12" angle="0.00" type="DEFAULT_VEHTYPE" speed="40.00" pos="5.37" lane="2/8to2/9_0" slope="0.00"/>
        <vehicle id="35" x="385.98" y="99.65" angle="270.00" type="DEFAULT_VEHTYPE" speed="7.83" pos="1.27" lane="4/1to3/1_0" slope="0.00"/>
        <vehicle id="36" x="691.99" y="684.35" angle="90.00" type="DEFAULT_VEHTYPE" speed="23.89" pos="1.24" lane="7/7to8/7_0" slope="0.00"/>
    </timestep>
    <timestep time="72.00">
        <vehicle id="1" x="1.65" y="215.95" angle="0.00" type="DEFAULT_VEHTYPE" speed="9.32" pos="15.20" lane="0/2to0/3_0" slope="0.00"/>
        <vehicle id="17" x="96.35" y="320.34" angle="180.00" type="DEFAULT_VEHTYPE" speed="28.85" pos="66.91" lane="1/4to1/3_0" slope="0.00"/>
        <vehicle id="29" x="560.56" y="880.35" angle="90.00" type="DEFAULT_VEHTYPE" speed="20.35" pos="65.81" lane="5/9to6/9_0" slope="0.00"/>
        <vehicle id="35" x="349.79" y="99.65" angle="270.00" type="DEFAULT_VEHTYPE" speed="12.06" pos="37.46" lane="4/1to3/1_0" slope="0.00"/>
        <vehicle id="36" x="773.19" y="684.35" angle="90.00" type="DEFAULT_VEHTYPE" speed="27.07" pos="82.44" lane="7/7to8/7_0" slope="0.00"/>
    </timestep>
    <timestep time="75.00">
        <vehicle id="1" x="1.65" y="257.17" angle="0.00" type="DEFAULT_VEHTYPE" speed="13.74" pos="56.42" lane="0/2to0/3_0" slope="0.00"/>
        <vehicle id="17" x="116.90" y="292.35" angle="90.00" type="DEFAULT_VEHTYPE" speed="15.35" pos="14.15" lane="1/3to2/3_0" slope="0.00"/>
        <vehicle id="29" x="586.35" y="857.84" angle="180.00" type="DEFAULT_VEHTYPE" speed="15.70" pos="19.41" lane="6/9to6/8_0" slope="0.00"/>
        <vehicle id="35" x="301.27" y="99.65" angle="270.00" type="DEFAULT_VEHTYPE" speed="16.17" pos="85.98" lane="4/1to3/1_0" slope="0.00"/>
        <vehicle id="36" x="813.89" y="684.35" angle="90.00" type="DEFAULT_VEHTYPE" speed="13.57" pos="25.14" lane="8/7to9/7_0" slope="0.00"/>
    </timestep>
    <timestep time="78.00">
        <vehicle id="1" x="1.65" y="315.38" angle="0.00" type="DEFAULT_VEHTYPE" speed="19.40" pos="16.63" lane="0/3to0/4_0" slope="0.00"/>
        <vehicle id="17" x="185.99" y="292.35" angle="90.00" type="DEFAULT_VEHTYPE" speed="23.03" pos="83.24" lane="1/3to2/3_0" slope="0.00"/>
        <vehicle id="29" x="586.35" y="791.74" angle="180.00" type="DEFAULT_VEHTYPE" speed="22.03" pos="85.51" lane="6/9to6/8_0" slope="0.00"/>
        <vehicle id="35" x="240.82" y="99.65" angle="270.00" type="DEFAULT_VEHTYPE" speed="20.15" pos="48.43" lane="3/1to2/1_0" slope="0.00"/>
        <vehicle id="36" x="867.35" y="684.35" angle="90.00" type="DEFAULT_VEHTYPE" speed="17.82" pos="78.60" lane="8/7to9/7_0" slope="0.00"/>
    </timestep>
    <timestep time="81.00">
        <vehicle id="1" x="1.65" y="387.31" angle="0.00" type="DEFAULT_VEHTYPE" speed="23.98" pos="0.06" lane=":0/4_7_0" slope="0.00"/>
        <vehicle id="35" x="197.65" y="116.20" angle="0.00" type="DEFAULT_VEHTYPE" speed="19.51" pos="13.45" lane="2/1to2/2_0" slope="0.00"/>
        <vehicle id="36" x="879.87" y="683.09" angle="105.44" type="DEFAULT_VEHTYPE" speed="4.32" pos="3.06" lane=":9/7_12_0" slope="0.00"/>
    </timestep>
    <timestep time="84.00">
        <vehicle id="1" x="1.65" y="480.77" angle="0.00" type="DEFAULT_VEHTYPE" speed="31.15" pos="84.02" lane="0/4to0/5_0" slope="0.00"/>
        <vehicle id="35" x="197.65" y="187.85" angle="0.00" type="DEFAULT_VEHTYPE" speed="23.88" pos="85.10" lane="2/1to2/2_0" slope="0.00"/>
        <vehicle id="36" x="880.35" y="654.60" angle="180.00" type="DEFAULT_VEHTYPE" speed="9.53" pos="26.65" lane="9/7to9/6_0" slope="0.00"/>
    </timestep>
    <timestep time="87.00">
        <vehicle id="1" x="6.54" y="586.35" angle="72.88" type="DEFAULT_VEHTYPE" speed="36.42" pos="1.79" lane="0/6to1/6_0" slope="0.00"/>
        <vehicle id="35" x="197.65" y="276.93" angle="0.00" type="DEFAULT_VEHTYPE" speed="29.69" pos="76.18" lane="2/2to2/3_0" slope="0.00"/>
        <vehicle id="36" x="880.35" y="607.27" angle="180.00" type="DEFAULT_VEHTYPE" speed="15.78" pos="73.98" lane="9/7to9/6_0" slope="0.00"/>
    </timestep>
    <timestep time="90.00">
        <vehicle id="35" x="198.05" y="388.96" angle="4.65" type="DEFAULT_VEHTYPE" speed="37.37" pos="1.78" lane=":2/4_8_0" slope="0.00"/>
    </timestep>
    <timestep time="93.00"/>
    <timestep time="96.00"/>
    <timestep time="99.00"/>
    <timestep time="102.00"/>
    <timestep time="105.00"/>
    <timestep time="108.00"/>
    <timestep time="111.00"/>
    <timestep time="114.00"/>
    <timestep time="117.00"/>
    <timestep time="120.00"/>
    <timestep time="123.00"/>
    <timestep time="126.00"/>
    <timestep time="129.00"/>
    <timestep time="132.00"/>
    <timestep time="135.00"/>
    <timestep time="138.00"/>
    <timestep time="141.00"/>
    <timestep time="144.00"/>
    <timestep time="147.00"/>
    <timestep time="150.00"/>
    <timestep time="153.00"/>
    <timestep time="156.00"/>
    <timestep time="159.00"/>
    <timestep time="162.00"/>
    <timestep time="165.00"/>
    <timestep time="168.00"/>
    <timestep time="171.00"/>
    <timestep time="174.00"/>
    <timestep time="177.00"/>
    <timestep time="180.00"/>
    <timestep time="183.00"/>
    <timestep time="186.00"/>
    <timestep time="189.00"/>
    <timestep time="192.00"/>
    <timestep time="195.00"/>
    <timestep time="198.00"/>
    <timestep time="201.00"/>
    <timestep time="204.00"/>
    <timestep time="207.00"/>
    <timestep time="210.00"/>
    <timestep time="213.00"/>
    <timestep time="216.00"/>
    <timestep time="219.00"/>
    <timestep time="222.00"/>
    <timestep time="225.00"/>
    <timestep time="228.00"/>
    <timestep time="231.00"/>
    <timestep time="234.00"/>
    <timestep time="237.00"/>
    <timestep time="240.00"/>
    <timestep time="243.00"/>
    <timestep time="246.00"/>
    <timestep time="249.00"/>
</fcd-export>
