<?xml version="1.0" encoding="UTF-8"?>

<!-- generated on Thu May  3 23:43:57 2018 by SUMO Version 0.32.0
<?xml version="1.0" encoding="UTF-8"?>

<configuration xmlns:xsi="http://www.w3.org/2001/XMLSchema-instance" xsi:noNamespaceSchemaLocation="http://sumo.dlr.de/xsd/sumoConfiguration.xsd">

    <input>
        <net-file value="mapgrid.net.xml"/>
        <route-files value="route.rou.xml"/>
    </input>

    <output>
        <fcd-output value="skenario.xml"/>
    </output>

    <time>
        <begin value="0"/>
        <end value="250"/>
        <step-length value="3"/>
    </time>

    <gui_only>
        <tracker-interval value="3"/>
    </gui_only>

</configuration>
-->

<fcd-export xmlns:xsi="http://www.w3.org/2001/XMLSchema-instance" xsi:noNamespaceSchemaLocation="http://sumo.dlr.de/xsd/fcd_file.xsd">
    <timestep time="0.00">
        <vehicle id="0" x="475.60" y="194.35" angle="90.00" type="DEFAULT_VEHTYPE" speed="3.21" pos="78.85" lane="4/2to5/2_0" slope="0.00"/>
        <vehicle id="1" x="978.35" y="618.19" angle="180.00" type="DEFAULT_VEHTYPE" speed="25.00" pos="63.06" lane="10/7to10/6_0" slope="0.00"/>
    </timestep>
    <timestep time="3.00">
        <vehicle id="0" x="479.40" y="194.35" angle="90.00" type="DEFAULT_VEHTYPE" speed="1.26" pos="82.65" lane="4/2to5/2_0" slope="0.00"/>
        <vehicle id="1" x="931.23" y="589.65" angle="270.00" type="DEFAULT_VEHTYPE" speed="24.82" pos="44.02" lane="10/6to9/6_0" slope="0.00"/>
        <vehicle id="2" x="194.35" y="139.04" angle="180.00" type="DEFAULT_VEHTYPE" speed="19.20" pos="52.21" lane="2/2to2/1_0" slope="0.00"/>
        <vehicle id="3" x="579.39" y="99.65" angle="270.00" type="DEFAULT_VEHTYPE" speed="25.00" pos="3.86" lane="6/1to5/1_0" slope="0.00"/>
        <vehicle id="4" x="713.47" y="295.65" angle="270.00" type="DEFAULT_VEHTYPE" speed="15.81" pos="65.78" lane="8/3to7/3_0" slope="0.00"/>
        <vehicle id="5" x="659.35" y="491.65" angle="270.00" type="DEFAULT_VEHTYPE" speed="25.00" pos="21.90" lane="7/5to6/5_0" slope="0.00"/>
    </timestep>
    <timestep time="6.00">
        <vehicle id="0" x="480.45" y="194.35" angle="90.00" type="DEFAULT_VEHTYPE" speed="0.35" pos="83.70" lane="4/2to5/2_0" slope="0.00"/>
        <vehicle id="1" x="876.29" y="589.65" angle="270.00" type="DEFAULT_VEHTYPE" speed="18.31" pos="0.96" lane="9/6to8/6_0" slope="0.00"/>
        <vehicle id="2" x="197.65" y="120.89" angle="0.00" type="DEFAULT_VEHTYPE" speed="19.75" pos="18.14" lane="2/1to2/2_0" slope="0.00"/>
        <vehicle id="3" x="512.26" y="99.65" angle="270.00" type="DEFAULT_VEHTYPE" speed="22.38" pos="70.99" lane="6/1to5/1_0" slope="0.00"/>
        <vehicle id="4" x="671.42" y="295.65" angle="270.00" type="DEFAULT_VEHTYPE" speed="14.02" pos="9.83" lane="7/3to6/3_0" slope="0.00"/>
        <vehicle id="5" x="589.80" y="491.65" angle="270.00" type="DEFAULT_VEHTYPE" speed="23.18" pos="2.95" lane=":6/5_5_0" slope="0.00"/>
        <vehicle id="6" x="687.65" y="642.87" angle="0.00" type="DEFAULT_VEHTYPE" speed="19.72" pos="50.12" lane="7/6to7/7_0" slope="0.00"/>
        <vehicle id="7" x="687.65" y="812.16" angle="0.00" type="DEFAULT_VEHTYPE" speed="25.00" pos="23.41" lane="7/8to7/9_0" slope="0.00"/>
        <vehicle id="8" x="197.65" y="598.08" angle="0.00" type="DEFAULT_VEHTYPE" speed="25.00" pos="5.33" lane="2/6to2/7_0" slope="0.00"/>
    </timestep>
    <timestep time="9.00">
        <vehicle id="0" x="480.45" y="194.35" angle="90.00" type="DEFAULT_VEHTYPE" speed="0.00" pos="83.70" lane="4/2to5/2_0" slope="0.00"/>
        <vehicle id="1" x="809.29" y="589.65" angle="270.00" type="DEFAULT_VEHTYPE" speed="22.33" pos="67.96" lane="9/6to8/6_0" slope="0.00"/>
        <vehicle id="10" x="978.35" y="548.15" angle="180.00" type="DEFAULT_VEHTYPE" speed="25.00" pos="35.10" lane="10/6to10/5_0" slope="0.00"/>
        <vehicle id="11" x="829.08" y="883.65" angle="270.00" type="DEFAULT_VEHTYPE" speed="20.21" pos="48.17" lane="9/9to8/9_0" slope="0.00"/>
        <vehicle id="2" x="197.65" y="195.35" angle="0.00" type="DEFAULT_VEHTYPE" speed="24.82" pos="4.10" lane=":2/2_9_0" slope="0.00"/>
        <vehicle id="3" x="472.60" y="99.65" angle="270.00" type="DEFAULT_VEHTYPE" speed="13.22" pos="12.65" lane="5/1to4/1_0" slope="0.00"/>
        <vehicle id="4" x="609.56" y="295.65" angle="270.00" type="DEFAULT_VEHTYPE" speed="20.62" pos="71.69" lane="7/3to6/3_0" slope="0.00"/>
        <vehicle id="5" x="520.80" y="491.65" angle="270.00" type="DEFAULT_VEHTYPE" speed="23.00" pos="62.45" lane="6/5to5/5_0" slope="0.00"/>
        <vehicle id="6" x="684.35" y="674.55" angle="180.00" type="DEFAULT_VEHTYPE" speed="16.64" pos="6.70" lane="7/7to7/6_0" slope="0.00"/>
        <vehicle id="7" x="687.50" y="877.47" angle="358.30" type="DEFAULT_VEHTYPE" speed="21.79" pos="0.27" lane=":7/9_11_0" slope="0.00"/>
        <vehicle id="8" x="197.65" y="665.67" angle="0.00" type="DEFAULT_VEHTYPE" speed="22.53" pos="72.92" lane="2/6to2/7_0" slope="0.00"/>
        <vehicle id="9" x="475.30" y="782.35" angle="90.00" type="DEFAULT_VEHTYPE" speed="3.31" pos="78.55" lane="4/8to5/8_0" slope="0.00"/>
    </timestep>
    <timestep time="12.00">
        <vehicle id="0" x="483.48" y="194.35" angle="90.00" type="DEFAULT_VEHTYPE" speed="1.01" pos="86.73" lane="4/2to5/2_0" slope="0.00"/>
        <vehicle id="1" x="763.96" y="589.65" angle="270.00" type="DEFAULT_VEHTYPE" speed="15.11" pos="15.29" lane="8/6to7/6_0" slope="0.00"/>
        <vehicle id="10" x="960.17" y="491.65" angle="270.00" type="DEFAULT_VEHTYPE" speed="24.50" pos="15.08" lane="10/5to9/5_0" slope="0.00"/>
        <vehicle id="11" x="773.35" y="883.65" angle="270.00" type="DEFAULT_VEHTYPE" speed="18.58" pos="5.90" lane="8/9to7/9_0" slope="0.00"/>
        <vehicle id="12" x="978.35" y="105.89" angle="180.00" type="DEFAULT_VEHTYPE" speed="25.00" pos="85.36" lane="10/2to10/1_0" slope="0.00"/>
        <vehicle id="13" x="322.12" y="684.35" angle="90.00" type="DEFAULT_VEHTYPE" speed="25.00" pos="23.37" lane="3/7to4/7_0" slope="0.00"/>
        <vehicle id="14" x="785.65" y="318.50" angle="0.00" type="DEFAULT_VEHTYPE" speed="25.00" pos="19.75" lane="8/3to8/4_0" slope="0.00"/>
        <vehicle id="2" x="197.65" y="259.16" angle="0.00" type="DEFAULT_VEHTYPE" speed="21.27" pos="58.41" lane="2/2to2/3_0" slope="0.00"/>
        <vehicle id="3" x="411.39" y="99.65" angle="270.00" type="DEFAULT_VEHTYPE" speed="20.40" pos="73.86" lane="5/1to4/1_0" slope="0.00"/>
        <vehicle id="4" x="570.18" y="295.65" angle="270.00" type="DEFAULT_VEHTYPE" speed="13.13" pos="13.07" lane="6/3to5/3_0" slope="0.00"/>
        <vehicle id="5" x="471.31" y="491.65" angle="270.00" type="DEFAULT_VEHTYPE" speed="16.50" pos="13.94" lane="5/5to4/5_0" slope="0.00"/>
        <vehicle id="6" x="684.35" y="609.25" angle="180.00" type="DEFAULT_VEHTYPE" speed="21.76" pos="72.00" lane="7/7to7/6_0" slope="0.00"/>
        <vehicle id="7" x="684.35" y="810.68" angle="180.00" type="DEFAULT_VEHTYPE" speed="23.71" pos="66.57" lane="7/9to7/8_0" slope="0.00"/>
        <vehicle id="8" x="194.35" y="666.80" angle="180.00" type="DEFAULT_VEHTYPE" speed="11.62" pos="14.45" lane="2/7to2/6_0" slope="0.00"/>
        <vehicle id="9" x="483.68" y="782.35" angle="90.00" type="DEFAULT_VEHTYPE" speed="2.79" pos="86.93" lane="4/8to5/8_0" slope="0.00"/>
    </timestep>
    <timestep time="15.00">
        <vehicle id="0" x="491.65" y="213.13" angle="0.00" type="DEFAULT_VEHTYPE" speed="8.16" pos="12.38" lane="5/2to5/3_0" slope="0.00"/>
        <vehicle id="1" x="696.28" y="589.65" angle="270.00" type="DEFAULT_VEHTYPE" speed="22.56" pos="82.97" lane="8/6to7/6_0" slope="0.00"/>
        <vehicle id="10" x="896.40" y="491.65" angle="270.00" type="DEFAULT_VEHTYPE" speed="21.26" pos="78.85" lane="10/5to9/5_0" slope="0.00"/>
        <vehicle id="11" x="701.95" y="883.65" angle="270.00" type="DEFAULT_VEHTYPE" speed="23.80" pos="77.30" lane="8/9to7/9_0" slope="0.00"/>
        <vehicle id="12" x="914.15" y="99.65" angle="270.00" type="DEFAULT_VEHTYPE" speed="23.08" pos="61.10" lane="10/1to9/1_0" slope="0.00"/>
        <vehicle id="13" x="390.27" y="684.88" angle="83.85" type="DEFAULT_VEHTYPE" speed="22.74" pos="3.08" lane=":4/7_14_0" slope="0.00"/>
        <vehicle id="14" x="784.51" y="391.29" angle="346.49" type="DEFAULT_VEHTYPE" speed="24.34" pos="4.28" lane=":8/4_10_0" slope="0.00"/>
        <vehicle id="15" x="782.35" y="792.74" angle="180.00" type="DEFAULT_VEHTYPE" speed="25.00" pos="84.51" lane="8/9to8/8_0" slope="0.00"/>
        <vehicle id="16" x="510.98" y="488.35" angle="90.00" type="DEFAULT_VEHTYPE" speed="25.00" pos="16.23" lane="5/5to6/5_0" slope="0.00"/>
        <vehicle id="17" x="551.54" y="880.35" angle="90.00" type="DEFAULT_VEHTYPE" speed="18.05" pos="56.79" lane="5/9to6/9_0" slope="0.00"/>
        <vehicle id="2" x="197.65" y="327.19" angle="0.00" type="DEFAULT_VEHTYPE" speed="22.67" pos="28.44" lane="2/3to2/4_0" slope="0.00"/>
        <vehicle id="3" x="393.65" y="117.70" angle="0.00" type="DEFAULT_VEHTYPE" speed="11.53" pos="14.95" lane="4/1to4/2_0" slope="0.00"/>
        <vehicle id="4" x="515.22" y="295.65" angle="270.00" type="DEFAULT_VEHTYPE" speed="18.32" pos="68.03" lane="6/3to5/3_0" slope="0.00"/>
        <vehicle id="5" x="406.52" y="491.65" angle="270.00" type="DEFAULT_VEHTYPE" speed="21.60" pos="78.73" lane="5/5to4/5_0" slope="0.00"/>
        <vehicle id="6" x="684.35" y="537.08" angle="180.00" type="DEFAULT_VEHTYPE" speed="24.06" pos="46.17" lane="7/6to7/5_0" slope="0.00"/>
        <vehicle id="7" x="684.35" y="746.62" angle="180.00" type="DEFAULT_VEHTYPE" speed="21.35" pos="32.63" lane="7/8to7/7_0" slope="0.00"/>
        <vehicle id="8" x="194.35" y="616.93" angle="180.00" type="DEFAULT_VEHTYPE" speed="16.62" pos="64.32" lane="2/7to2/6_0" slope="0.00"/>
        <vehicle id="9" x="488.35" y="763.54" angle="180.00" type="DEFAULT_VEHTYPE" speed="7.43" pos="15.71" lane="5/8to5/7_0" slope="0.00"/>
    </timestep>
    <timestep time="18.00">
        <vehicle id="0" x="491.65" y="258.90" angle="0.00" type="DEFAULT_VEHTYPE" speed="15.26" pos="58.15" lane="5/2to5/3_0" slope="0.00"/>
        <vehicle id="1" x="684.35" y="571.92" angle="180.00" type="DEFAULT_VEHTYPE" speed="9.06" pos="11.33" lane="7/6to7/5_0" slope="0.00"/>
        <vehicle id="10" x="873.13" y="491.65" angle="270.00" type="DEFAULT_VEHTYPE" speed="7.76" pos="4.12" lane="9/5to8/5_0" slope="0.00"/>
        <vehicle id="11" x="671.05" y="883.65" angle="270.00" type="DEFAULT_VEHTYPE" speed="10.30" pos="10.20" lane="7/9to6/9_0" slope="0.00"/>
        <vehicle id="12" x="865.72" y="99.65" angle="270.00" type="DEFAULT_VEHTYPE" speed="16.14" pos="11.53" lane="9/1to8/1_0" slope="0.00"/>
        <vehicle id="13" x="393.65" y="756.40" angle="0.00" type="DEFAULT_VEHTYPE" speed="24.30" pos="65.65" lane="4/7to4/8_0" slope="0.00"/>
        <vehicle id="14" x="710.84" y="393.65" angle="270.00" type="DEFAULT_VEHTYPE" speed="24.82" pos="68.41" lane="8/4to7/4_0" slope="0.00"/>
        <vehicle id="15" x="717.36" y="785.65" angle="270.00" type="DEFAULT_VEHTYPE" speed="23.63" pos="61.89" lane="8/8to7/8_0" slope="0.00"/>
        <vehicle id="16" x="584.62" y="489.45" angle="76.54" type="DEFAULT_VEHTYPE" speed="24.69" pos="1.79" lane=":6/5_15_0" slope="0.00"/>
        <vehicle id="17" x="586.35" y="868.33" angle="180.00" type="DEFAULT_VEHTYPE" speed="15.21" pos="8.92" lane="6/9to6/8_0" slope="0.00"/>
        <vehicle id="18" x="96.35" y="165.58" angle="180.00" type="DEFAULT_VEHTYPE" speed="25.00" pos="25.67" lane="1/2to1/1_0" slope="0.00"/>
        <vehicle id="19" x="684.35" y="621.19" angle="180.00" type="DEFAULT_VEHTYPE" speed="17.23" pos="60.06" lane="7/7to7/6_0" slope="0.00"/>
        <vehicle id="2" x="197.65" y="401.18" angle="0.00" type="DEFAULT_VEHTYPE" speed="24.66" pos="4.43" lane="2/4to2/5_0" slope="0.00"/>
        <vehicle id="20" x="883.65" y="728.20" angle="0.00" type="DEFAULT_VEHTYPE" speed="22.89" pos="37.45" lane="9/7to9/8_0" slope="0.00"/>
        <vehicle id="3" x="393.65" y="164.08" angle="0.00" type="DEFAULT_VEHTYPE" speed="15.46" pos="61.33" lane="4/1to4/2_0" slope="0.00"/>
        <vehicle id="4" x="491.65" y="318.61" angle="0.00" type="DEFAULT_VEHTYPE" speed="15.11" pos="19.86" lane="5/3to5/4_0" slope="0.00"/>
        <vehicle id="5" x="382.22" y="491.65" angle="270.00" type="DEFAULT_VEHTYPE" speed="8.10" pos="5.03" lane="4/5to3/5_0" slope="0.00"/>
        <vehicle id="6" x="684.35" y="465.75" angle="180.00" type="DEFAULT_VEHTYPE" speed="23.78" pos="19.50" lane="7/5to7/4_0" slope="0.00"/>
        <vehicle id="7" x="684.35" y="678.26" angle="180.00" type="DEFAULT_VEHTYPE" speed="22.79" pos="2.99" lane="7/7to7/6_0" slope="0.00"/>
        <vehicle id="8" x="194.35" y="546.92" angle="180.00" type="DEFAULT_VEHTYPE" speed="23.34" pos="36.33" lane="2/6to2/5_0" slope="0.00"/>
        <vehicle id="9" x="488.35" y="721.82" angle="180.00" type="DEFAULT_VEHTYPE" speed="13.90" pos="57.43" lane="5/8to5/7_0" slope="0.00"/>
    </timestep>
    <timestep time="21.00">
        <vehicle id="0" x="491.65" y="320.88" angle="0.00" type="DEFAULT_VEHTYPE" speed="20.66" pos="22.13" lane="5/3to5/4_0" slope="0.00"/>
        <vehicle id="1" x="684.35" y="531.00" angle="180.00" type="DEFAULT_VEHTYPE" speed="13.64" pos="52.25" lane="7/6to7/5_0" slope="0.00"/>
        <vehicle id="10" x="837.89" y="491.65" angle="270.00" type="DEFAULT_VEHTYPE" speed="11.75" pos="39.36" lane="9/5to8/5_0" slope="0.00"/>
        <vehicle id="11" x="617.03" y="883.65" angle="270.00" type="DEFAULT_VEHTYPE" speed="18.01" pos="64.22" lane="7/9to6/9_0" slope="0.00"/>
        <vehicle id="12" x="804.72" y="99.65" angle="270.00" type="DEFAULT_VEHTYPE" speed="20.33" pos="72.53" lane="9/1to8/1_0" slope="0.00"/>
        <vehicle id="13" x="438.14" y="782.35" angle="90.00" type="DEFAULT_VEHTYPE" speed="23.08" pos="41.39" lane="4/8to5/8_0" slope="0.00"/>
        <vehicle id="14" x="670.45" y="393.65" angle="270.00" type="DEFAULT_VEHTYPE" speed="13.46" pos="10.80" lane="7/4to6/4_0" slope="0.00"/>
        <vehicle id="15" x="677.33" y="785.65" angle="270.00" type="DEFAULT_VEHTYPE" speed="13.34" pos="3.92" lane="7/8to6/8_0" slope="0.00"/>
        <vehicle id="16" x="519.59" y="491.65" angle="270.00" type="DEFAULT_VEHTYPE" speed="22.23" pos="63.66" lane="6/5to5/5_0" slope="0.00"/>
        <vehicle id="17" x="586.35" y="804.62" angle="180.00" type="DEFAULT_VEHTYPE" speed="21.24" pos="72.63" lane="6/9to6/8_0" slope="0.00"/>
        <vehicle id="18" x="98.20" y="97.80" angle="158.34" type="DEFAULT_VEHTYPE" speed="22.76" pos="0.18" lane=":1/1_16_0" slope="0.00"/>
        <vehicle id="19" x="687.65" y="602.68" angle="0.00" type="DEFAULT_VEHTYPE" speed="14.40" pos="9.93" lane="7/6to7/7_0" slope="0.00"/>
        <vehicle id="2" x="197.65" y="474.95" angle="0.00" type="DEFAULT_VEHTYPE" speed="24.59" pos="78.20" lane="2/4to2/5_0" slope="0.00"/>
        <vehicle id="20" x="877.44" y="785.62" angle="289.07" type="DEFAULT_VEHTYPE" speed="20.39" pos="4.85" lane=":9/8_18_0" slope="0.00"/>
        <vehicle id="21" x="292.35" y="655.03" angle="180.00" type="DEFAULT_VEHTYPE" speed="25.00" pos="26.22" lane="3/7to3/6_0" slope="0.00"/>
        <vehicle id="22" x="978.35" y="154.87" angle="180.00" type="DEFAULT_VEHTYPE" speed="23.15" pos="36.38" lane="10/2to10/1_0" slope="0.00"/>
        <vehicle id="23" x="99.65" y="819.09" angle="0.00" type="DEFAULT_VEHTYPE" speed="25.00" pos="30.34" lane="1/8to1/9_0" slope="0.00"/>
        <vehicle id="3" x="393.65" y="229.30" angle="0.00" type="DEFAULT_VEHTYPE" speed="21.74" pos="28.55" lane="4/2to4/3_0" slope="0.00"/>
        <vehicle id="4" x="491.65" y="380.49" angle="0.00" type="DEFAULT_VEHTYPE" speed="20.63" pos="81.74" lane="5/3to5/4_0" slope="0.00"/>
        <vehicle id="5" x="338.79" y="491.65" angle="270.00" type="DEFAULT_VEHTYPE" speed="14.47" pos="48.46" lane="4/5to3/5_0" slope="0.00"/>
        <vehicle id="6" x="684.35" y="394.29" angle="180.00" type="DEFAULT_VEHTYPE" speed="23.82" pos="2.46" lane=":7/4_1_0" slope="0.00"/>
        <vehicle id="7" x="684.35" y="610.57" angle="180.00" type="DEFAULT_VEHTYPE" speed="22.56" pos="70.68" lane="7/7to7/6_0" slope="0.00"/>
        <vehicle id="8" x="194.35" y="476.80" angle="180.00" type="DEFAULT_VEHTYPE" speed="23.37" pos="8.45" lane="2/5to2/4_0" slope="0.00"/>
        <vehicle id="9" x="488.35" y="662.71" angle="180.00" type="DEFAULT_VEHTYPE" speed="19.70" pos="18.54" lane="5/7to5/6_0" slope="0.00"/>
    </timestep>
    <timestep time="24.00">
        <vehicle id="0" x="493.00" y="389.93" angle="16.66" type="DEFAULT_VEHTYPE" speed="23.18" pos="3.17" lane=":5/4_8_0" slope="0.00"/>
        <vehicle id="1" x="684.35" y="474.86" angle="180.00" type="DEFAULT_VEHTYPE" speed="18.71" pos="10.39" lane="7/5to7/4_0" slope="0.00"/>
        <vehicle id="10" x="788.39" y="491.65" angle="270.00" type="DEFAULT_VEHTYPE" speed="16.50" pos="0.36" lane=":8/5_5_0" slope="0.00"/>
        <vehicle id="11" x="571.81" y="883.65" angle="270.00" type="DEFAULT_VEHTYPE" speed="15.07" pos="11.44" lane="6/9to5/9_0" slope="0.00"/>
        <vehicle id="12" x="770.79" y="99.65" angle="270.00" type="DEFAULT_VEHTYPE" speed="11.31" pos="8.46" lane="8/1to7/1_0" slope="0.00"/>
        <vehicle id="13" x="491.65" y="789.05" angle="16.16" type="DEFAULT_VEHTYPE" speed="19.24" pos="0.30" lane="5/8to5/9_0" slope="0.00"/>
        <vehicle id="14" x="618.10" y="393.65" angle="270.00" type="DEFAULT_VEHTYPE" speed="17.45" pos="63.15" lane="7/4to6/4_0" slope="0.00"/>
        <vehicle id="15" x="615.69" y="785.65" angle="270.00" type="DEFAULT_VEHTYPE" speed="20.54" pos="65.56" lane="7/8to6/8_0" slope="0.00"/>
        <vehicle id="16" x="480.55" y="491.65" angle="270.00" type="DEFAULT_VEHTYPE" speed="13.01" pos="4.70" lane="5/5to4/5_0" slope="0.00"/>
        <vehicle id="17" x="586.35" y="731.27" angle="180.00" type="DEFAULT_VEHTYPE" speed="24.45" pos="47.98" lane="6/8to6/7_0" slope="0.00"/>
        <vehicle id="18" x="162.30" y="96.35" angle="90.00" type="DEFAULT_VEHTYPE" speed="21.47" pos="59.55" lane="1/1to2/1_0" slope="0.00"/>
        <vehicle id="19" x="687.65" y="664.70" angle="0.00" type="DEFAULT_VEHTYPE" speed="20.67" pos="71.95" lane="7/6to7/7_0" slope="0.00"/>
        <vehicle id="2" x="197.65" y="541.62" angle="0.00" type="DEFAULT_VEHTYPE" speed="22.22" pos="46.87" lane="2/5to2/6_0" slope="0.00"/>
        <vehicle id="20" x="806.47" y="785.65" angle="270.00" type="DEFAULT_VEHTYPE" speed="23.66" pos="70.78" lane="9/8to8/8_0" slope="0.00"/>
        <vehicle id="21" x="292.35" y="586.92" angle="180.00" type="DEFAULT_VEHTYPE" speed="22.70" pos="5.83" lane=":3/6_1_0" slope="0.00"/>
        <vehicle id="22" x="981.65" y="111.97" angle="0.00" type="DEFAULT_VEHTYPE" speed="22.05" pos="9.22" lane="10/1to10/2_0" slope="0.00"/>
        <vehicle id="23" x="99.65" y="886.33" angle="0.00" type="DEFAULT_VEHTYPE" speed="22.41" pos="9.08" lane=":1/9_9_0" slope="0.00"/>
        <vehicle id="24" x="586.35" y="558.71" angle="180.00" type="DEFAULT_VEHTYPE" speed="25.00" pos="24.54" lane="6/6to6/5_0" slope="0.00"/>
        <vehicle id="25" x="589.65" y="332.33" angle="0.00" type="DEFAULT_VEHTYPE" speed="23.85" pos="33.58" lane="6/3to6/4_0" slope="0.00"/>
        <vehicle id="26" x="491.65" y="849.01" angle="0.00" type="DEFAULT_VEHTYPE" speed="17.19" pos="60.26" lane="5/8to5/9_0" slope="0.00"/>
        <vehicle id="3" x="393.65" y="293.99" angle="0.00" type="DEFAULT_VEHTYPE" speed="21.56" pos="4.74" lane=":4/3_9_0" slope="0.00"/>
        <vehicle id="4" x="491.65" y="454.30" angle="0.00" type="DEFAULT_VEHTYPE" speed="24.60" pos="57.55" lane="5/4to5/5_0" slope="0.00"/>
        <vehicle id="5" x="286.20" y="491.65" angle="270.00" type="DEFAULT_VEHTYPE" speed="17.53" pos="3.05" lane="3/5to2/5_0" slope="0.00"/>
        <vehicle id="6" x="684.35" y="319.79" angle="180.00" type="DEFAULT_VEHTYPE" speed="24.83" pos="67.46" lane="7/4to7/3_0" slope="0.00"/>
        <vehicle id="7" x="684.35" y="537.03" angle="180.00" type="DEFAULT_VEHTYPE" speed="24.52" pos="46.22" lane="7/6to7/5_0" slope="0.00"/>
        <vehicle id="8" x="194.35" y="407.41" angle="180.00" type="DEFAULT_VEHTYPE" speed="23.13" pos="77.84" lane="2/5to2/4_0" slope="0.00"/>
        <vehicle id="9" x="488.35" y="592.06" angle="180.00" type="DEFAULT_VEHTYPE" speed="23.55" pos="0.69" lane=":5/6_1_0" slope="0.00"/>
    </timestep>
    <timestep time="27.00">
        <vehicle id="0" x="556.87" y="390.35" angle="90.00" type="DEFAULT_VEHTYPE" speed="21.32" pos="62.12" lane="5/4to6/4_0" slope="0.00"/>
        <vehicle id="1" x="684.35" y="407.37" angle="180.00" type="DEFAULT_VEHTYPE" speed="22.50" pos="77.88" lane="7/5to7/4_0" slope="0.00"/>
        <vehicle id="10" x="715.66" y="491.65" angle="270.00" type="DEFAULT_VEHTYPE" speed="24.24" pos="63.59" lane="8/5to7/5_0" slope="0.00"/>
        <vehicle id="11" x="514.67" y="883.65" angle="270.00" type="DEFAULT_VEHTYPE" speed="19.05" pos="68.58" lane="6/9to5/9_0" slope="0.00"/>
        <vehicle id="12" x="724.03" y="99.65" angle="270.00" type="DEFAULT_VEHTYPE" speed="15.59" pos="55.22" lane="8/1to7/1_0" slope="0.00"/>
        <vehicle id="13" x="491.65" y="864.04" angle="0.00" type="DEFAULT_VEHTYPE" speed="25.00" pos="75.29" lane="5/8to5/9_0" slope="0.00"/>
        <vehicle id="14" x="569.99" y="393.65" angle="270.00" type="DEFAULT_VEHTYPE" speed="16.04" pos="13.26" lane="6/4to5/4_0" slope="0.00"/>
        <vehicle id="15" x="586.35" y="775.03" angle="181.26" type="DEFAULT_VEHTYPE" speed="12.49" pos="4.22" lane="6/8to6/7_0" slope="0.00"/>
        <vehicle id="16" x="425.82" y="491.65" angle="270.00" type="DEFAULT_VEHTYPE" speed="18.24" pos="59.43" lane="5/5to4/5_0" slope="0.00"/>
        <vehicle id="17" x="586.35" y="658.23" angle="180.00" type="DEFAULT_VEHTYPE" speed="24.35" pos="23.02" lane="6/7to6/6_0" slope="0.00"/>
        <vehicle id="18" x="203.56" y="96.35" angle="90.00" type="DEFAULT_VEHTYPE" speed="13.75" pos="2.81" lane="2/1to3/1_0" slope="0.00"/>
        <vehicle id="19" x="737.50" y="684.35" angle="90.00" type="DEFAULT_VEHTYPE" speed="22.76" pos="46.75" lane="7/7to8/7_0" slope="0.00"/>
        <vehicle id="2" x="197.65" y="606.24" angle="0.00" type="DEFAULT_VEHTYPE" speed="21.54" pos="13.49" lane="2/6to2/7_0" slope="0.00"/>
        <vehicle id="20" x="763.02" y="785.65" angle="270.00" type="DEFAULT_VEHTYPE" speed="14.48" pos="16.23" lane="8/8to7/8_0" slope="0.00"/>
        <vehicle id="21" x="292.35" y="516.74" angle="180.00" type="DEFAULT_VEHTYPE" speed="23.39" pos="66.51" lane="3/6to3/5_0" slope="0.00"/>
        <vehicle id="22" x="981.65" y="176.33" angle="0.00" type="DEFAULT_VEHTYPE" speed="21.45" pos="73.58" lane="10/1to10/2_0" slope="0.00"/>
        <vehicle id="23" x="99.65" y="955.64" angle="0.00" type="DEFAULT_VEHTYPE" speed="23.10" pos="68.89" lane="1/9to1/10_0" slope="0.00"/>
        <vehicle id="24" x="586.20" y="493.68" angle="181.72" type="DEFAULT_VEHTYPE" speed="21.68" pos="1.08" lane=":6/5_0_0" slope="0.00"/>
        <vehicle id="25" x="480.25" y="393.65" angle="270.00" type="DEFAULT_VEHTYPE" speed="25.00" pos="5.00" lane="5/4to4/4_0" slope="0.00"/>
        <vehicle id="26" x="472.34" y="883.65" angle="270.00" type="DEFAULT_VEHTYPE" speed="17.16" pos="12.91" lane="5/9to4/9_0" slope="0.00"/>
        <vehicle id="27" x="488.35" y="20.74" angle="180.00" type="DEFAULT_VEHTYPE" speed="14.12" pos="72.51" lane="5/1to5/0_0" slope="0.00"/>
        <vehicle id="3" x="393.65" y="364.94" angle="0.00" type="DEFAULT_VEHTYPE" speed="23.65" pos="66.19" lane="4/3to4/4_0" slope="0.00"/>
        <vehicle id="4" x="491.65" y="519.69" angle="0.00" type="DEFAULT_VEHTYPE" speed="21.80" pos="24.94" lane="5/5to5/6_0" slope="0.00"/>
        <vehicle id="5" x="217.63" y="491.65" angle="270.00" type="DEFAULT_VEHTYPE" speed="22.86" pos="71.62" lane="3/5to2/5_0" slope="0.00"/>
        <vehicle id="6" x="684.35" y="250.29" angle="180.00" type="DEFAULT_VEHTYPE" speed="23.17" pos="38.96" lane="7/3to7/2_0" slope="0.00"/>
        <vehicle id="7" x="684.35" y="467.67" angle="180.00" type="DEFAULT_VEHTYPE" speed="23.12" pos="17.58" lane="7/5to7/4_0" slope="0.00"/>
        <vehicle id="8" x="194.35" y="339.35" angle="180.00" type="DEFAULT_VEHTYPE" speed="22.69" pos="47.90" lane="2/4to2/3_0" slope="0.00"/>
        <vehicle id="9" x="488.35" y="526.39" angle="180.00" type="DEFAULT_VEHTYPE" speed="21.89" pos="56.86" lane="5/6to5/5_0" slope="0.00"/>
    </timestep>
    <timestep time="30.00">
        <vehicle id="0" x="601.75" y="390.35" angle="90.00" type="DEFAULT_VEHTYPE" speed="14.96" pos="9.00" lane="6/4to7/4_0" slope="0.00"/>
        <vehicle id="1" x="684.35" y="336.97" angle="180.00" type="DEFAULT_VEHTYPE" speed="23.47" pos="50.28" lane="7/4to7/3_0" slope="0.00"/>
        <vehicle id="10" x="670.97" y="491.65" angle="270.00" type="DEFAULT_VEHTYPE" speed="14.90" pos="10.28" lane="7/5to6/5_0" slope="0.00"/>
        <vehicle id="11" x="480.38" y="883.65" angle="270.00" type="DEFAULT_VEHTYPE" speed="11.43" pos="4.87" lane="5/9to4/9_0" slope="0.00"/>
        <vehicle id="12" x="677.94" y="99.65" angle="270.00" type="DEFAULT_VEHTYPE" speed="15.36" pos="3.31" lane="7/1to6/1_0" slope="0.00"/>
        <vehicle id="14" x="503.71" y="393.65" angle="270.00" type="DEFAULT_VEHTYPE" speed="22.09" pos="79.54" lane="6/4to5/4_0" slope="0.00"/>
        <vehicle id="15" x="586.35" y="717.93" angle="180.00" type="DEFAULT_VEHTYPE" speed="19.03" pos="61.32" lane="6/8to6/7_0" slope="0.00"/>
        <vehicle id="16" x="383.59" y="491.65" angle="270.00" type="DEFAULT_VEHTYPE" speed="14.08" pos="3.66" lane="4/5to3/5_0" slope="0.00"/>
        <vehicle id="17" x="586.35" y="585.07" angle="180.00" type="DEFAULT_VEHTYPE" speed="24.39" pos="7.68" lane=":6/6_1_0" slope="0.00"/>
        <vehicle id="18" x="267.08" y="96.35" angle="90.00" type="DEFAULT_VEHTYPE" speed="21.17" pos="66.33" lane="2/1to3/1_0" slope="0.00"/>
        <vehicle id="19" x="797.32" y="684.35" angle="90.00" type="DEFAULT_VEHTYPE" speed="19.94" pos="8.57" lane="8/7to9/7_0" slope="0.00"/>
        <vehicle id="2" x="197.65" y="671.86" angle="0.00" type="DEFAULT_VEHTYPE" speed="21.87" pos="79.11" lane="2/6to2/7_0" slope="0.00"/>
        <vehicle id="20" x="698.81" y="785.65" angle="270.00" type="DEFAULT_VEHTYPE" speed="21.40" pos="80.44" lane="8/8to7/8_0" slope="0.00"/>
        <vehicle id="21" x="314.91" y="488.35" angle="90.00" type="DEFAULT_VEHTYPE" speed="16.15" pos="16.16" lane="3/5to4/5_0" slope="0.00"/>
        <vehicle id="22" x="981.65" y="247.43" angle="0.00" type="DEFAULT_VEHTYPE" speed="23.70" pos="46.68" lane="10/2to10/3_0" slope="0.00"/>
        <vehicle id="23" x="120.48" y="978.35" angle="90.00" type="DEFAULT_VEHTYPE" speed="14.11" pos="17.73" lane="1/10to2/10_0" slope="0.00"/>
        <vehicle id="24" x="522.93" y="491.65" angle="270.00" type="DEFAULT_VEHTYPE" speed="21.41" pos="60.32" lane="6/5to5/5_0" slope="0.00"/>
        <vehicle id="25" x="408.18" y="393.65" angle="270.00" type="DEFAULT_VEHTYPE" speed="24.02" pos="77.07" lane="5/4to4/4_0" slope="0.00"/>
        <vehicle id="26" x="398.80" y="883.65" angle="270.00" type="DEFAULT_VEHTYPE" speed="24.51" pos="86.45" lane="5/9to4/9_0" slope="0.00"/>
        <vehicle id="27" x="467.70" y="1.65" angle="270.00" type="DEFAULT_VEHTYPE" speed="12.85" pos="17.55" lane="5/0to4/0_0" slope="0.00"/>
        <vehicle id="3" x="437.66" y="390.35" angle="90.00" type="DEFAULT_VEHTYPE" speed="22.74" pos="40.91" lane="4/4to5/4_0" slope="0.00"/>
        <vehicle id="4" x="491.65" y="586.23" angle="0.00" type="DEFAULT_VEHTYPE" speed="22.18" pos="2.98" lane=":5/6_9_0" slope="0.00"/>
        <vehicle id="5" x="194.35" y="475.19" angle="180.00" type="DEFAULT_VEHTYPE" speed="12.42" pos="10.06" lane="2/5to2/4_0" slope="0.00"/>
        <vehicle id="6" x="693.07" y="194.35" angle="94.37" type="DEFAULT_VEHTYPE" speed="20.73" pos="2.32" lane="7/2to8/2_0" slope="0.00"/>
        <vehicle id="7" x="684.35" y="404.34" angle="180.00" type="DEFAULT_VEHTYPE" speed="21.11" pos="80.91" lane="7/5to7/4_0" slope="0.00"/>
        <vehicle id="8" x="194.35" y="266.78" angle="180.00" type="DEFAULT_VEHTYPE" speed="24.19" pos="22.47" lane="2/3to2/2_0" slope="0.00"/>
        <vehicle id="9" x="488.35" y="452.91" angle="180.00" type="DEFAULT_VEHTYPE" speed="24.49" pos="32.34" lane="5/5to5/4_0" slope="0.00"/>
    </timestep>
    <timestep time="33.00">
        <vehicle id="0" x="664.70" y="390.35" angle="90.00" type="DEFAULT_VEHTYPE" speed="20.98" pos="71.95" lane="6/4to7/4_0" slope="0.00"/>
        <vehicle id="1" x="684.35" y="266.69" angle="180.00" type="DEFAULT_VEHTYPE" speed="23.43" pos="22.56" lane="7/3to7/2_0" slope="0.00"/>
        <vehicle id="10" x="602.96" y="491.65" angle="270.00" type="DEFAULT_VEHTYPE" speed="22.67" pos="78.29" lane="7/5to6/5_0" slope="0.00"/>
        <vehicle id="11" x="425.28" y="883.65" angle="270.00" type="DEFAULT_VEHTYPE" speed="18.37" pos="59.97" lane="5/9to4/9_0" slope="0.00"/>
        <vehicle id="12" x="615.12" y="99.65" angle="270.00" type="DEFAULT_VEHTYPE" speed="20.94" pos="66.13" lane="7/1to6/1_0" slope="0.00"/>
        <vehicle id="14" x="477.93" y="393.65" angle="270.00" type="DEFAULT_VEHTYPE" speed="8.59" pos="7.32" lane="5/4to4/4_0" slope="0.00"/>
        <vehicle id="15" x="586.35" y="645.16" angle="180.00" type="DEFAULT_VEHTYPE" speed="24.26" pos="36.09" lane="6/7to6/6_0" slope="0.00"/>
        <vehicle id="16" x="318.36" y="491.65" angle="270.00" type="DEFAULT_VEHTYPE" speed="21.74" pos="68.89" lane="4/5to3/5_0" slope="0.00"/>
        <vehicle id="17" x="586.35" y="516.96" angle="180.00" type="DEFAULT_VEHTYPE" speed="22.71" pos="66.29" lane="6/6to6/5_0" slope="0.00"/>
        <vehicle id="18" x="303.27" y="96.35" angle="90.00" type="DEFAULT_VEHTYPE" speed="12.06" pos="4.52" lane="3/1to4/1_0" slope="0.00"/>
        <vehicle id="19" x="864.52" y="684.35" angle="90.00" type="DEFAULT_VEHTYPE" speed="22.40" pos="75.77" lane="8/7to9/7_0" slope="0.00"/>
        <vehicle id="2" x="258.57" y="684.35" angle="90.00" type="DEFAULT_VEHTYPE" speed="24.07" pos="57.82" lane="2/7to3/7_0" slope="0.00"/>
        <vehicle id="20" x="675.10" y="785.65" angle="270.00" type="DEFAULT_VEHTYPE" speed="7.90" pos="6.15" lane="7/8to6/8_0" slope="0.00"/>
        <vehicle id="21" x="379.70" y="488.35" angle="90.00" type="DEFAULT_VEHTYPE" speed="21.60" pos="80.95" lane="3/5to4/5_0" slope="0.00"/>
        <vehicle id="22" x="981.65" y="313.66" angle="0.00" type="DEFAULT_VEHTYPE" speed="22.08" pos="14.91" lane="10/3to10/4_0" slope="0.00"/>
        <vehicle id="23" x="177.58" y="978.35" angle="90.00" type="DEFAULT_VEHTYPE" speed="19.03" pos="74.83" lane="1/10to2/10_0" slope="0.00"/>
        <vehicle id="24" x="488.35" y="474.55" angle="180.00" type="DEFAULT_VEHTYPE" speed="16.40" pos="10.70" lane="5/5to5/4_0" slope="0.00"/>
        <vehicle id="25" x="390.35" y="377.43" angle="180.00" type="DEFAULT_VEHTYPE" speed="10.52" pos="9.82" lane="4/4to4/3_0" slope="0.00"/>
        <vehicle id="26" x="334.81" y="883.65" angle="270.00" type="DEFAULT_VEHTYPE" speed="21.33" pos="52.44" lane="4/9to3/9_0" slope="0.00"/>
        <vehicle id="27" x="417.26" y="1.65" angle="270.00" type="DEFAULT_VEHTYPE" speed="16.81" pos="67.99" lane="5/0to4/0_0" slope="0.00"/>
        <vehicle id="4" x="491.65" y="659.84" angle="0.00" type="DEFAULT_VEHTYPE" speed="24.53" pos="67.09" lane="5/6to5/7_0" slope="0.00"/>
        <vehicle id="5" x="194.35" y="415.53" angle="180.00" type="DEFAULT_VEHTYPE" speed="19.89" pos="69.72" lane="2/5to2/4_0" slope="0.00"/>
        <vehicle id="6" x="758.79" y="194.35" angle="90.00" type="DEFAULT_VEHTYPE" speed="21.91" pos="68.04" lane="7/2to8/2_0" slope="0.00"/>
        <vehicle id="7" x="628.79" y="393.65" angle="270.00" type="DEFAULT_VEHTYPE" speed="21.68" pos="52.46" lane="7/4to6/4_0" slope="0.00"/>
        <vehicle id="8" x="194.35" y="200.45" angle="180.00" type="DEFAULT_VEHTYPE" speed="22.11" pos="0.30" lane=":2/2_1_0" slope="0.00"/>
        <vehicle id="9" x="488.35" y="382.94" angle="180.00" type="DEFAULT_VEHTYPE" speed="23.32" pos="4.31" lane="5/4to5/3_0" slope="0.00"/>
    </timestep>
    <timestep time="36.00">
        <vehicle id="0" x="704.72" y="390.35" angle="90.00" type="DEFAULT_VEHTYPE" speed="13.34" pos="13.97" lane="7/4to8/4_0" slope="0.00"/>
        <vehicle id="1" x="684.35" y="195.31" angle="180.00" type="DEFAULT_VEHTYPE" speed="23.79" pos="5.44" lane=":7/2_1_0" slope="0.00"/>
        <vehicle id="10" x="575.46" y="491.65" angle="270.00" type="DEFAULT_VEHTYPE" speed="9.17" pos="7.79" lane="6/5to5/5_0" slope="0.00"/>
        <vehicle id="11" x="378.20" y="883.65" angle="270.00" type="DEFAULT_VEHTYPE" speed="15.69" pos="9.05" lane="4/9to3/9_0" slope="0.00"/>
        <vehicle id="12" x="574.23" y="99.65" angle="270.00" type="DEFAULT_VEHTYPE" speed="13.63" pos="9.02" lane="6/1to5/1_0" slope="0.00"/>
        <vehicle id="14" x="430.94" y="393.65" angle="270.00" type="DEFAULT_VEHTYPE" speed="15.66" pos="54.31" lane="5/4to4/4_0" slope="0.00"/>
        <vehicle id="15" x="586.35" y="574.21" angle="180.00" type="DEFAULT_VEHTYPE" speed="23.65" pos="9.04" lane="6/6to6/5_0" slope="0.00"/>
        <vehicle id="16" x="273.49" y="491.65" angle="270.00" type="DEFAULT_VEHTYPE" speed="14.96" pos="15.76" lane="3/5to2/5_0" slope="0.00"/>
        <vehicle id="17" x="586.35" y="444.44" angle="180.00" type="DEFAULT_VEHTYPE" speed="24.17" pos="40.81" lane="6/5to6/4_0" slope="0.00"/>
        <vehicle id="18" x="359.31" y="96.35" angle="90.00" type="DEFAULT_VEHTYPE" speed="18.68" pos="60.56" lane="3/1to4/1_0" slope="0.00"/>
        <vehicle id="20" x="636.90" y="785.65" angle="270.00" type="DEFAULT_VEHTYPE" speed="12.73" pos="44.35" lane="7/8to6/8_0" slope="0.00"/>
        <vehicle id="21" x="403.99" y="488.35" angle="90.00" type="DEFAULT_VEHTYPE" speed="8.10" pos="7.24" lane="4/5to5/5_0" slope="0.00"/>
        <vehicle id="22" x="981.65" y="377.70" angle="0.00" type="DEFAULT_VEHTYPE" speed="21.34" pos="78.95" lane="10/3to10/4_0" slope="0.00"/>
        <vehicle id="23" x="241.99" y="978.35" angle="90.00" type="DEFAULT_VEHTYPE" speed="21.47" pos="41.24" lane="2/10to3/10_0" slope="0.00"/>
        <vehicle id="24" x="488.35" y="402.51" angle="180.00" type="DEFAULT_VEHTYPE" speed="24.01" pos="82.74" lane="5/5to5/4_0" slope="0.00"/>
        <vehicle id="25" x="390.35" y="332.15" angle="180.00" type="DEFAULT_VEHTYPE" speed="15.09" pos="55.10" lane="4/4to4/3_0" slope="0.00"/>
        <vehicle id="26" x="282.69" y="883.65" angle="270.00" type="DEFAULT_VEHTYPE" speed="17.37" pos="6.56" lane="3/9to2/9_0" slope="0.00"/>
        <vehicle id="27" x="354.13" y="1.65" angle="270.00" type="DEFAULT_VEHTYPE" speed="21.04" pos="33.12" lane="4/0to3/0_0" slope="0.00"/>
        <vehicle id="4" x="491.65" y="734.68" angle="0.00" type="DEFAULT_VEHTYPE" speed="24.95" pos="43.93" lane="5/7to5/8_0" slope="0.00"/>
        <vehicle id="5" x="194.35" y="341.81" angle="180.00" type="DEFAULT_VEHTYPE" speed="24.57" pos="45.44" lane="2/4to2/3_0" slope="0.00"/>
        <vehicle id="6" x="793.41" y="194.35" angle="90.00" type="DEFAULT_VEHTYPE" speed="11.54" pos="4.66" lane="8/2to9/2_0" slope="0.00"/>
        <vehicle id="8" x="194.35" y="129.72" angle="180.00" type="DEFAULT_VEHTYPE" speed="23.57" pos="61.53" lane="2/2to2/1_0" slope="0.00"/>
        <vehicle id="9" x="488.35" y="314.68" angle="180.00" type="DEFAULT_VEHTYPE" speed="22.76" pos="72.57" lane="5/4to5/3_0" slope="0.00"/>
    </timestep>
    <timestep time="39.00">
        <vehicle id="0" x="762.56" y="390.35" angle="90.00" type="DEFAULT_VEHTYPE" speed="19.28" pos="71.81" lane="7/4to8/4_0" slope="0.00"/>
        <vehicle id="1" x="684.35" y="122.11" angle="180.00" type="DEFAULT_VEHTYPE" speed="24.40" pos="69.14" lane="7/2to7/1_0" slope="0.00"/>
        <vehicle id="10" x="532.79" y="491.65" angle="270.00" type="DEFAULT_VEHTYPE" speed="14.22" pos="50.46" lane="6/5to5/5_0" slope="0.00"/>
        <vehicle id="11" x="317.02" y="883.65" angle="270.00" type="DEFAULT_VEHTYPE" speed="20.39" pos="70.23" lane="4/9to3/9_0" slope="0.00"/>
        <vehicle id="12" x="516.76" y="99.65" angle="270.00" type="DEFAULT_VEHTYPE" speed="19.16" pos="66.49" lane="6/1to5/1_0" slope="0.00"/>
        <vehicle id="14" x="375.37" y="393.65" angle="270.00" type="DEFAULT_VEHTYPE" speed="18.53" pos="11.88" lane="4/4to3/4_0" slope="0.00"/>
        <vehicle id="15" x="586.35" y="509.60" angle="180.00" type="DEFAULT_VEHTYPE" speed="21.54" pos="73.65" lane="6/6to6/5_0" slope="0.00"/>
        <vehicle id="16" x="211.15" y="491.65" angle="270.00" type="DEFAULT_VEHTYPE" speed="20.78" pos="78.10" lane="3/5to2/5_0" slope="0.00"/>
        <vehicle id="17" x="586.35" y="377.08" angle="180.00" type="DEFAULT_VEHTYPE" speed="22.45" pos="10.17" lane="6/4to6/3_0" slope="0.00"/>
        <vehicle id="18" x="410.20" y="96.35" angle="90.00" type="DEFAULT_VEHTYPE" speed="16.96" pos="13.45" lane="4/1to5/1_0" slope="0.00"/>
        <vehicle id="20" x="586.03" y="785.65" angle="270.00" type="DEFAULT_VEHTYPE" speed="16.95" pos="6.72" lane=":6/8_5_0" slope="0.00"/>
        <vehicle id="21" x="447.18" y="488.35" angle="90.00" type="DEFAULT_VEHTYPE" speed="14.40" pos="50.43" lane="4/5to5/5_0" slope="0.00"/>
        <vehicle id="22" x="981.65" y="448.68" angle="0.00" type="DEFAULT_VEHTYPE" speed="23.66" pos="51.93" lane="10/4to10/5_0" slope="0.00"/>
        <vehicle id="23" x="311.39" y="978.35" angle="90.00" type="DEFAULT_VEHTYPE" speed="23.13" pos="12.64" lane="3/10to4/10_0" slope="0.00"/>
        <vehicle id="24" x="488.35" y="327.98" angle="180.00" type="DEFAULT_VEHTYPE" speed="24.85" pos="59.27" lane="5/4to5/3_0" slope="0.00"/>
        <vehicle id="26" x="211.13" y="883.65" angle="270.00" type="DEFAULT_VEHTYPE" speed="23.86" pos="78.12" lane="3/9to2/9_0" slope="0.00"/>
        <vehicle id="27" x="283.12" y="1.65" angle="270.00" type="DEFAULT_VEHTYPE" speed="23.67" pos="6.13" lane="3/0to2/0_0" slope="0.00"/>
        <vehicle id="4" x="476.19" y="785.65" angle="270.00" type="DEFAULT_VEHTYPE" speed="21.32" pos="9.06" lane="5/8to4/8_0" slope="0.00"/>
        <vehicle id="5" x="194.35" y="273.18" angle="180.00" type="DEFAULT_VEHTYPE" speed="22.88" pos="16.07" lane="2/3to2/2_0" slope="0.00"/>
        <vehicle id="6" x="842.12" y="194.35" angle="90.00" type="DEFAULT_VEHTYPE" speed="16.23" pos="53.37" lane="8/2to9/2_0" slope="0.00"/>
        <vehicle id="8" x="194.35" y="57.25" angle="180.00" type="DEFAULT_VEHTYPE" speed="24.16" pos="36.00" lane="2/1to2/0_0" slope="0.00"/>
        <vehicle id="9" x="488.35" y="243.01" angle="180.00" type="DEFAULT_VEHTYPE" speed="23.89" pos="46.24" lane="5/3to5/2_0" slope="0.00"/>
    </timestep>
    <timestep time="42.00">
        <vehicle id="0" x="797.71" y="390.35" angle="90.00" type="DEFAULT_VEHTYPE" speed="11.72" pos="8.96" lane="8/4to9/4_0" slope="0.00"/>
        <vehicle id="1" x="703.65" y="96.35" angle="90.00" type="DEFAULT_VEHTYPE" speed="14.19" pos="12.90" lane="7/1to8/1_0" slope="0.00"/>
        <vehicle id="10" x="491.65" y="509.97" angle="0.00" type="DEFAULT_VEHTYPE" speed="19.42" pos="15.22" lane="5/5to5/6_0" slope="0.00"/>
        <vehicle id="11" x="275.84" y="883.65" angle="270.00" type="DEFAULT_VEHTYPE" speed="13.72" pos="13.41" lane="3/9to2/9_0" slope="0.00"/>
        <vehicle id="12" x="481.59" y="99.65" angle="270.00" type="DEFAULT_VEHTYPE" speed="11.72" pos="3.66" lane="5/1to4/1_0" slope="0.00"/>
        <vehicle id="14" x="311.12" y="393.65" angle="270.00" type="DEFAULT_VEHTYPE" speed="21.42" pos="76.13" lane="4/4to3/4_0" slope="0.00"/>
        <vehicle id="15" x="589.65" y="518.19" angle="0.00" type="DEFAULT_VEHTYPE" speed="14.37" pos="23.44" lane="6/5to6/6_0" slope="0.00"/>
        <vehicle id="16" x="194.35" y="484.13" angle="191.02" type="DEFAULT_VEHTYPE" speed="7.28" pos="1.12" lane="2/5to2/4_0" slope="0.00"/>
        <vehicle id="17" x="586.35" y="312.91" angle="180.00" type="DEFAULT_VEHTYPE" speed="21.39" pos="74.34" lane="6/4to6/3_0" slope="0.00"/>
        <vehicle id="18" x="475.42" y="96.35" angle="90.00" type="DEFAULT_VEHTYPE" speed="21.74" pos="78.67" lane="4/1to5/1_0" slope="0.00"/>
        <vehicle id="20" x="520.43" y="785.65" angle="270.00" type="DEFAULT_VEHTYPE" speed="21.87" pos="62.82" lane="6/8to5/8_0" slope="0.00"/>
        <vehicle id="21" x="488.35" y="478.12" angle="180.00" type="DEFAULT_VEHTYPE" speed="16.73" pos="7.13" lane="5/5to5/4_0" slope="0.00"/>
        <vehicle id="22" x="981.65" y="514.35" angle="0.00" type="DEFAULT_VEHTYPE" speed="21.89" pos="19.60" lane="10/5to10/6_0" slope="0.00"/>
        <vehicle id="23" x="381.74" y="978.35" angle="90.00" type="DEFAULT_VEHTYPE" speed="23.45" pos="82.99" lane="3/10to4/10_0" slope="0.00"/>
        <vehicle id="24" x="451.22" y="295.65" angle="270.00" type="DEFAULT_VEHTYPE" speed="22.75" pos="34.03" lane="5/3to4/3_0" slope="0.00"/>
        <vehicle id="26" x="180.06" y="883.65" angle="270.00" type="DEFAULT_VEHTYPE" speed="10.36" pos="11.19" lane="2/9to1/9_0" slope="0.00"/>
        <vehicle id="27" x="210.27" y="1.65" angle="270.00" type="DEFAULT_VEHTYPE" speed="24.28" pos="78.98" lane="3/0to2/0_0" slope="0.00"/>
        <vehicle id="4" x="408.79" y="785.65" angle="270.00" type="DEFAULT_VEHTYPE" speed="22.47" pos="76.46" lane="5/8to4/8_0" slope="0.00"/>
        <vehicle id="5" x="194.35" y="203.66" angle="180.00" type="DEFAULT_VEHTYPE" speed="23.17" pos="85.59" lane="2/3to2/2_0" slope="0.00"/>
        <vehicle id="6" x="888.04" y="194.35" angle="90.00" type="DEFAULT_VEHTYPE" speed="15.31" pos="1.29" lane="9/2to10/2_0" slope="0.00"/>
        <vehicle id="8" x="197.79" y="-1.16" angle="139.28" type="DEFAULT_VEHTYPE" speed="19.94" pos="7.31" lane=":2/0_1_0" slope="0.00"/>
        <vehicle id="9" x="488.35" y="168.32" angle="180.00" type="DEFAULT_VEHTYPE" speed="24.90" pos="22.93" lane="5/2to5/1_0" slope="0.00"/>
    </timestep>
    <timestep time="45.00">
        <vehicle id="0" x="844.85" y="390.35" angle="90.00" type="DEFAULT_VEHTYPE" speed="15.72" pos="56.10" lane="8/4to9/4_0" slope="0.00"/>
        <vehicle id="1" x="759.67" y="96.35" angle="90.00" type="DEFAULT_VEHTYPE" speed="18.67" pos="68.92" lane="7/1to8/1_0" slope="0.00"/>
        <vehicle id="10" x="491.65" y="574.35" angle="0.00" type="DEFAULT_VEHTYPE" speed="21.46" pos="79.60" lane="5/5to5/6_0" slope="0.00"/>
        <vehicle id="11" x="219.38" y="883.65" angle="270.00" type="DEFAULT_VEHTYPE" speed="18.82" pos="69.87" lane="3/9to2/9_0" slope="0.00"/>
        <vehicle id="12" x="429.70" y="99.65" angle="270.00" type="DEFAULT_VEHTYPE" speed="17.30" pos="55.55" lane="5/1to4/1_0" slope="0.00"/>
        <vehicle id="14" x="287.37" y="393.65" angle="270.00" type="DEFAULT_VEHTYPE" speed="7.92" pos="1.88" lane="3/4to2/4_0" slope="0.00"/>
        <vehicle id="16" x="194.35" y="442.72" angle="180.00" type="DEFAULT_VEHTYPE" speed="13.80" pos="42.53" lane="2/5to2/4_0" slope="0.00"/>
        <vehicle id="17" x="586.35" y="249.07" angle="180.00" type="DEFAULT_VEHTYPE" speed="21.28" pos="40.18" lane="6/3to6/2_0" slope="0.00"/>
        <vehicle id="18" x="500.14" y="96.35" angle="90.00" type="DEFAULT_VEHTYPE" speed="8.24" pos="5.39" lane="5/1to6/1_0" slope="0.00"/>
        <vehicle id="20" x="482.08" y="785.65" angle="270.00" type="DEFAULT_VEHTYPE" speed="12.79" pos="3.17" lane="5/8to4/8_0" slope="0.00"/>
        <vehicle id="21" x="488.35" y="411.58" angle="180.00" type="DEFAULT_VEHTYPE" speed="22.18" pos="73.67" lane="5/5to5/4_0" slope="0.00"/>
        <vehicle id="22" x="981.65" y="578.92" angle="0.00" type="DEFAULT_VEHTYPE" speed="21.53" pos="84.17" lane="10/5to10/6_0" slope="0.00"/>
        <vehicle id="23" x="451.98" y="978.35" angle="90.00" type="DEFAULT_VEHTYPE" speed="23.41" pos="55.23" lane="4/10to5/10_0" slope="0.00"/>
        <vehicle id="26" x="130.60" y="883.65" angle="270.00" type="DEFAULT_VEHTYPE" speed="16.49" pos="60.65" lane="2/9to1/9_0" slope="0.00"/>
        <vehicle id="27" x="197.65" y="61.68" angle="0.00" type="DEFAULT_VEHTYPE" speed="23.82" pos="56.93" lane="2/0to2/1_0" slope="0.00"/>
        <vehicle id="5" x="194.35" y="134.59" angle="180.00" type="DEFAULT_VEHTYPE" speed="23.03" pos="56.66" lane="2/2to2/1_0" slope="0.00"/>
        <vehicle id="6" x="948.12" y="194.35" angle="90.00" type="DEFAULT_VEHTYPE" speed="20.03" pos="61.37" lane="9/2to10/2_0" slope="0.00"/>
        <vehicle id="8" x="268.66" y="-1.65" angle="90.00" type="DEFAULT_VEHTYPE" speed="23.64" pos="67.91" lane="2/0to3/0_0" slope="0.00"/>
        <vehicle id="9" x="491.65" y="103.60" angle="64.40" type="DEFAULT_VEHTYPE" speed="23.75" pos="0.85" lane="5/1to5/2_0" slope="0.00"/>
    </timestep>
    <timestep time="48.00">
        <vehicle id="10" x="464.20" y="589.65" angle="270.00" type="DEFAULT_VEHTYPE" speed="13.42" pos="21.05" lane="5/6to4/6_0" slope="0.00"/>
        <vehicle id="11" x="194.35" y="862.02" angle="180.00" type="DEFAULT_VEHTYPE" speed="14.73" pos="15.23" lane="2/9to2/8_0" slope="0.00"/>
        <vehicle id="12" x="386.26" y="99.65" angle="270.00" type="DEFAULT_VEHTYPE" speed="14.48" pos="0.99" lane="4/1to3/1_0" slope="0.00"/>
        <vehicle id="14" x="248.47" y="393.65" angle="270.00" type="DEFAULT_VEHTYPE" speed="12.97" pos="40.78" lane="3/4to2/4_0" slope="0.00"/>
        <vehicle id="16" x="194.35" y="387.91" angle="180.00" type="DEFAULT_VEHTYPE" speed="18.27" pos="8.84" lane=":2/4_1_0" slope="0.00"/>
        <vehicle id="17" x="586.35" y="181.05" angle="180.00" type="DEFAULT_VEHTYPE" speed="22.68" pos="10.20" lane="6/2to6/1_0" slope="0.00"/>
        <vehicle id="18" x="537.83" y="96.35" angle="90.00" type="DEFAULT_VEHTYPE" speed="12.56" pos="43.08" lane="5/1to6/1_0" slope="0.00"/>
        <vehicle id="20" x="423.38" y="785.65" angle="270.00" type="DEFAULT_VEHTYPE" speed="19.57" pos="61.87" lane="5/8to4/8_0" slope="0.00"/>
        <vehicle id="22" x="981.65" y="647.60" angle="0.00" type="DEFAULT_VEHTYPE" speed="22.89" pos="54.85" lane="10/6to10/7_0" slope="0.00"/>
        <vehicle id="23" x="518.07" y="978.35" angle="90.00" type="DEFAULT_VEHTYPE" speed="22.03" pos="23.32" lane="5/10to6/10_0" slope="0.00"/>
        <vehicle id="26" x="96.35" y="864.74" angle="180.00" type="DEFAULT_VEHTYPE" speed="16.89" pos="12.51" lane="1/9to1/8_0" slope="0.00"/>
        <vehicle id="27" x="197.65" y="126.16" angle="0.00" type="DEFAULT_VEHTYPE" speed="21.49" pos="23.41" lane="2/1to2/2_0" slope="0.00"/>
        <vehicle id="8" x="339.20" y="-1.65" angle="90.00" type="DEFAULT_VEHTYPE" speed="23.52" pos="40.45" lane="3/0to4/0_0" slope="0.00"/>
        <vehicle id="9" x="491.65" y="170.65" angle="0.00" type="DEFAULT_VEHTYPE" speed="22.35" pos="67.90" lane="5/1to5/2_0" slope="0.00"/>
    </timestep>
    <timestep time="51.00">
        <vehicle id="10" x="402.91" y="589.65" angle="270.00" type="DEFAULT_VEHTYPE" speed="20.43" pos="82.34" lane="5/6to4/6_0" slope="0.00"/>
        <vehicle id="11" x="194.35" y="795.76" angle="180.00" type="DEFAULT_VEHTYPE" speed="22.09" pos="81.49" lane="2/9to2/8_0" slope="0.00"/>
        <vehicle id="12" x="320.40" y="99.65" angle="270.00" type="DEFAULT_VEHTYPE" speed="21.95" pos="66.85" lane="4/1to3/1_0" slope="0.00"/>
        <vehicle id="14" x="195.71" y="393.65" angle="270.00" type="DEFAULT_VEHTYPE" speed="17.59" pos="5.04" lane=":2/4_5_0" slope="0.00"/>
        <vehicle id="16" x="194.35" y="313.87" angle="180.00" type="DEFAULT_VEHTYPE" speed="24.68" pos="73.38" lane="2/4to2/3_0" slope="0.00"/>
        <vehicle id="17" x="586.35" y="106.75" angle="180.00" type="DEFAULT_VEHTYPE" speed="24.76" pos="84.50" lane="6/2to6/1_0" slope="0.00"/>
        <vehicle id="18" x="597.16" y="96.35" angle="90.00" type="DEFAULT_VEHTYPE" speed="19.78" pos="4.41" lane="6/1to7/1_0" slope="0.00"/>
        <vehicle id="20" x="376.32" y="785.65" angle="270.00" type="DEFAULT_VEHTYPE" speed="15.69" pos="10.93" lane="4/8to3/8_0" slope="0.00"/>
        <vehicle id="22" x="981.65" y="717.65" angle="0.00" type="DEFAULT_VEHTYPE" speed="23.35" pos="26.90" lane="10/7to10/8_0" slope="0.00"/>
        <vehicle id="23" x="582.54" y="978.35" angle="90.00" type="DEFAULT_VEHTYPE" speed="21.49" pos="87.79" lane="5/10to6/10_0" slope="0.00"/>
        <vehicle id="26" x="96.35" y="800.45" angle="180.00" type="DEFAULT_VEHTYPE" speed="21.43" pos="76.80" lane="1/9to1/8_0" slope="0.00"/>
        <vehicle id="27" x="197.65" y="189.75" angle="0.00" type="DEFAULT_VEHTYPE" speed="21.20" pos="87.00" lane="2/1to2/2_0" slope="0.00"/>
        <vehicle id="8" x="403.89" y="-1.65" angle="90.00" type="DEFAULT_VEHTYPE" speed="21.56" pos="7.14" lane="4/0to5/0_0" slope="0.00"/>
    </timestep>
    <timestep time="54.00">
        <vehicle id="11" x="194.35" y="726.96" angle="180.00" type="DEFAULT_VEHTYPE" speed="22.93" pos="52.29" lane="2/8to2/7_0" slope="0.00"/>
        <vehicle id="12" x="275.26" y="99.65" angle="270.00" type="DEFAULT_VEHTYPE" speed="15.05" pos="13.99" lane="3/1to2/1_0" slope="0.00"/>
        <vehicle id="14" x="123.48" y="393.65" angle="270.00" type="DEFAULT_VEHTYPE" speed="24.08" pos="67.77" lane="2/4to1/4_0" slope="0.00"/>
        <vehicle id="16" x="194.35" y="250.23" angle="180.00" type="DEFAULT_VEHTYPE" speed="21.21" pos="39.02" lane="2/3to2/2_0" slope="0.00"/>
        <vehicle id="17" x="612.22" y="96.35" angle="90.00" type="DEFAULT_VEHTYPE" speed="11.26" pos="19.47" lane="6/1to7/1_0" slope="0.00"/>
        <vehicle id="18" x="669.50" y="96.35" angle="90.00" type="DEFAULT_VEHTYPE" speed="24.11" pos="76.75" lane="6/1to7/1_0" slope="0.00"/>
        <vehicle id="20" x="316.80" y="785.65" angle="270.00" type="DEFAULT_VEHTYPE" speed="19.84" pos="70.45" lane="4/8to3/8_0" slope="0.00"/>
        <vehicle id="22" x="981.65" y="785.60" angle="0.00" type="DEFAULT_VEHTYPE" speed="22.65" pos="6.35" lane=":10/8_3_0" slope="0.00"/>
        <vehicle id="23" x="647.54" y="978.35" angle="90.00" type="DEFAULT_VEHTYPE" speed="21.67" pos="54.79" lane="6/10to7/10_0" slope="0.00"/>
        <vehicle id="26" x="96.35" y="729.65" angle="180.00" type="DEFAULT_VEHTYPE" speed="23.60" pos="49.60" lane="1/8to1/7_0" slope="0.00"/>
        <vehicle id="27" x="197.65" y="261.61" angle="0.00" type="DEFAULT_VEHTYPE" speed="23.95" pos="60.86" lane="2/2to2/3_0" slope="0.00"/>
        <vehicle id="8" x="468.87" y="-1.65" angle="90.00" type="DEFAULT_VEHTYPE" speed="21.66" pos="72.12" lane="4/0to5/0_0" slope="0.00"/>
    </timestep>
    <timestep time="57.00">
        <vehicle id="11" x="194.35" y="652.02" angle="180.00" type="DEFAULT_VEHTYPE" speed="24.98" pos="29.23" lane="2/7to2/6_0" slope="0.00"/>
        <vehicle id="12" x="213.05" y="99.65" angle="270.00" type="DEFAULT_VEHTYPE" speed="20.74" pos="76.20" lane="3/1to2/1_0" slope="0.00"/>
        <vehicle id="14" x="96.35" y="382.34" angle="180.15" type="DEFAULT_VEHTYPE" speed="11.99" pos="4.91" lane="1/4to1/3_0" slope="0.00"/>
        <vehicle id="16" x="210.61" y="194.35" angle="90.00" type="DEFAULT_VEHTYPE" speed="23.22" pos="9.86" lane="2/2to3/2_0" slope="0.00"/>
        <vehicle id="17" x="661.98" y="96.35" angle="90.00" type="DEFAULT_VEHTYPE" speed="16.59" pos="69.23" lane="6/1to7/1_0" slope="0.00"/>
        <vehicle id="18" x="701.33" y="96.35" angle="90.00" type="DEFAULT_VEHTYPE" speed="10.61" pos="10.58" lane="7/1to8/1_0" slope="0.00"/>
        <vehicle id="20" x="279.02" y="785.65" angle="270.00" type="DEFAULT_VEHTYPE" speed="12.59" pos="10.23" lane="3/8to2/8_0" slope="0.00"/>
        <vehicle id="22" x="981.65" y="853.92" angle="0.00" type="DEFAULT_VEHTYPE" speed="22.78" pos="65.17" lane="10/8to10/9_0" slope="0.00"/>
        <vehicle id="23" x="713.97" y="978.35" angle="90.00" type="DEFAULT_VEHTYPE" speed="22.14" pos="23.22" lane="7/10to8/10_0" slope="0.00"/>
        <vehicle id="26" x="96.35" y="664.84" angle="180.00" type="DEFAULT_VEHTYPE" speed="21.60" pos="16.41" lane="1/7to1/6_0" slope="0.00"/>
        <vehicle id="27" x="197.65" y="332.76" angle="0.00" type="DEFAULT_VEHTYPE" speed="23.72" pos="34.01" lane="2/3to2/4_0" slope="0.00"/>
    </timestep>
    <timestep time="60.00">
        <vehicle id="11" x="205.69" y="586.35" angle="90.10" type="DEFAULT_VEHTYPE" speed="24.84" pos="4.94" lane="2/6to3/6_0" slope="0.00"/>
        <vehicle id="12" x="191.33" y="99.65" angle="270.00" type="DEFAULT_VEHTYPE" speed="7.24" pos="9.42" lane=":2/1_5_0" slope="0.00"/>
        <vehicle id="14" x="96.35" y="334.10" angle="180.00" type="DEFAULT_VEHTYPE" speed="16.08" pos="53.15" lane="1/4to1/3_0" slope="0.00"/>
        <vehicle id="16" x="278.07" y="194.35" angle="90.00" type="DEFAULT_VEHTYPE" speed="22.49" pos="77.32" lane="2/2to3/2_0" slope="0.00"/>
        <vehicle id="17" x="706.57" y="96.35" angle="90.00" type="DEFAULT_VEHTYPE" speed="14.86" pos="15.82" lane="7/1to8/1_0" slope="0.00"/>
        <vehicle id="18" x="747.66" y="96.35" angle="90.00" type="DEFAULT_VEHTYPE" speed="15.44" pos="56.91" lane="7/1to8/1_0" slope="0.00"/>
        <vehicle id="20" x="227.33" y="785.65" angle="270.00" type="DEFAULT_VEHTYPE" speed="17.23" pos="61.92" lane="3/8to2/8_0" slope="0.00"/>
        <vehicle id="22" x="965.03" y="883.65" angle="270.00" type="DEFAULT_VEHTYPE" speed="14.62" pos="10.22" lane="10/9to9/9_0" slope="0.00"/>
        <vehicle id="23" x="788.36" y="978.35" angle="90.00" type="DEFAULT_VEHTYPE" speed="24.80" pos="9.11" lane=":8/10_7_0" slope="0.00"/>
        <vehicle id="26" x="96.35" y="591.48" angle="180.00" type="DEFAULT_VEHTYPE" speed="24.46" pos="1.27" lane=":1/6_1_0" slope="0.00"/>
        <vehicle id="27" x="197.65" y="396.40" angle="0.00" type="DEFAULT_VEHTYPE" speed="21.21" pos="9.15" lane=":2/4_9_0" slope="0.00"/>
    </timestep>
    <timestep time="63.00">
        <vehicle id="11" x="275.69" y="586.35" angle="90.00" type="DEFAULT_VEHTYPE" speed="23.33" pos="74.94" lane="2/6to3/6_0" slope="0.00"/>
        <vehicle id="12" x="151.18" y="99.65" angle="270.00" type="DEFAULT_VEHTYPE" speed="13.38" pos="40.07" lane="2/1to1/1_0" slope="0.00"/>
        <vehicle id="14" x="96.35" y="271.69" angle="180.00" type="DEFAULT_VEHTYPE" speed="20.81" pos="17.56" lane="1/3to1/2_0" slope="0.00"/>
        <vehicle id="17" x="760.32" y="96.35" angle="90.00" type="DEFAULT_VEHTYPE" speed="17.92" pos="69.57" lane="7/1to8/1_0" slope="0.00"/>
        <vehicle id="18" x="792.87" y="96.35" angle="90.00" type="DEFAULT_VEHTYPE" speed="15.07" pos="4.12" lane="8/1to9/1_0" slope="0.00"/>
        <vehicle id="20" x="194.35" y="768.36" angle="180.00" type="DEFAULT_VEHTYPE" speed="15.93" pos="10.89" lane="2/8to2/7_0" slope="0.00"/>
        <vehicle id="22" x="899.52" y="883.65" angle="270.00" type="DEFAULT_VEHTYPE" speed="21.84" pos="75.73" lane="10/9to9/9_0" slope="0.00"/>
        <vehicle id="23" x="857.24" y="978.35" angle="90.00" type="DEFAULT_VEHTYPE" speed="22.96" pos="68.49" lane="8/10to9/10_0" slope="0.00"/>
        <vehicle id="26" x="96.35" y="522.55" angle="180.00" type="DEFAULT_VEHTYPE" speed="22.98" pos="60.70" lane="1/6to1/5_0" slope="0.00"/>
        <vehicle id="27" x="197.65" y="465.03" angle="0.00" type="DEFAULT_VEHTYPE" speed="22.88" pos="68.28" lane="2/4to2/5_0" slope="0.00"/>
    </timestep>
    <timestep time="66.00">
        <vehicle id="12" x="98.48" y="99.65" angle="270.00" type="DEFAULT_VEHTYPE" speed="17.57" pos="4.27" lane=":1/1_5_0" slope="0.00"/>
        <vehicle id="14" x="96.35" y="198.09" angle="180.00" type="DEFAULT_VEHTYPE" speed="24.53" pos="2.66" lane=":1/2_1_0" slope="0.00"/>
        <vehicle id="17" x="799.84" y="96.35" angle="90.00" type="DEFAULT_VEHTYPE" speed="13.17" pos="11.09" lane="8/1to9/1_0" slope="0.00"/>
        <vehicle id="18" x="860.51" y="96.35" angle="90.00" type="DEFAULT_VEHTYPE" speed="22.55" pos="71.76" lane="8/1to9/1_0" slope="0.00"/>
        <vehicle id="20" x="194.35" y="700.21" angle="180.00" type="DEFAULT_VEHTYPE" speed="22.72" pos="79.04" lane="2/8to2/7_0" slope="0.00"/>
        <vehicle id="22" x="883.65" y="894.00" angle="0.00" type="DEFAULT_VEHTYPE" speed="8.34" pos="7.25" lane="9/9to9/10_0" slope="0.00"/>
        <vehicle id="23" x="856.47" y="981.65" angle="270.00" type="DEFAULT_VEHTYPE" speed="15.21" pos="20.78" lane="9/10to8/10_0" slope="0.00"/>
        <vehicle id="26" x="96.35" y="458.48" angle="180.00" type="DEFAULT_VEHTYPE" speed="21.35" pos="26.77" lane="1/5to1/4_0" slope="0.00"/>
        <vehicle id="27" x="197.65" y="532.86" angle="0.00" type="DEFAULT_VEHTYPE" speed="22.61" pos="38.11" lane="2/5to2/6_0" slope="0.00"/>
    </timestep>
    <timestep time="69.00">
        <vehicle id="12" x="33.56" y="99.65" angle="270.00" type="DEFAULT_VEHTYPE" speed="21.64" pos="59.69" lane="1/1to0/1_0" slope="0.00"/>
        <vehicle id="14" x="96.35" y="124.36" angle="180.00" type="DEFAULT_VEHTYPE" speed="24.57" pos="66.89" lane="1/2to1/1_0" slope="0.00"/>
        <vehicle id="17" x="861.98" y="96.35" angle="90.00" type="DEFAULT_VEHTYPE" speed="20.71" pos="73.23" lane="8/1to9/1_0" slope="0.00"/>
        <vehicle id="18" x="901.33" y="96.35" angle="90.00" type="DEFAULT_VEHTYPE" speed="13.61" pos="14.58" lane="9/1to10/1_0" slope="0.00"/>
        <vehicle id="20" x="194.35" y="628.66" angle="180.00" type="DEFAULT_VEHTYPE" speed="23.85" pos="52.59" lane="2/7to2/6_0" slope="0.00"/>
        <vehicle id="22" x="883.65" y="932.92" angle="0.00" type="DEFAULT_VEHTYPE" speed="12.98" pos="46.17" lane="9/9to9/10_0" slope="0.00"/>
        <vehicle id="23" x="789.67" y="981.65" angle="270.00" type="DEFAULT_VEHTYPE" speed="22.26" pos="87.58" lane="9/10to8/10_0" slope="0.00"/>
        <vehicle id="26" x="96.35" y="386.81" angle="180.00" type="DEFAULT_VEHTYPE" speed="23.89" pos="0.44" lane="1/4to1/3_0" slope="0.00"/>
        <vehicle id="27" x="194.35" y="571.44" angle="180.00" type="DEFAULT_VEHTYPE" speed="22.34" pos="11.81" lane="2/6to2/5_0" slope="0.00"/>
    </timestep>
    <timestep time="72.00">
        <vehicle id="12" x="1.65" y="110.03" angle="0.00" type="DEFAULT_VEHTYPE" speed="13.70" pos="7.28" lane="0/1to0/2_0" slope="0.00"/>
        <vehicle id="17" x="892.55" y="96.35" angle="90.00" type="DEFAULT_VEHTYPE" speed="10.19" pos="5.80" lane="9/1to10/1_0" slope="0.00"/>
        <vehicle id="18" x="960.99" y="96.35" angle="90.00" type="DEFAULT_VEHTYPE" speed="19.89" pos="74.24" lane="9/1to10/1_0" slope="0.00"/>
        <vehicle id="20" x="197.65" y="602.70" angle="0.00" type="DEFAULT_VEHTYPE" speed="16.89" pos="9.95" lane="2/6to2/7_0" slope="0.00"/>
        <vehicle id="22" x="877.99" y="981.54" angle="294.61" type="DEFAULT_VEHTYPE" speed="17.30" pos="9.57" lane=":9/10_4_0" slope="0.00"/>
        <vehicle id="26" x="96.35" y="322.02" angle="180.00" type="DEFAULT_VEHTYPE" speed="21.60" pos="65.23" lane="1/4to1/3_0" slope="0.00"/>
        <vehicle id="27" x="194.35" y="504.26" angle="180.00" type="DEFAULT_VEHTYPE" speed="22.40" pos="78.99" lane="2/6to2/5_0" slope="0.00"/>
    </timestep>
    <timestep time="75.00">
        <vehicle id="12" x="1.65" y="171.13" angle="0.00" type="DEFAULT_VEHTYPE" speed="20.36" pos="68.38" lane="0/1to0/2_0" slope="0.00"/>
        <vehicle id="17" x="935.73" y="96.35" angle="90.00" type="DEFAULT_VEHTYPE" speed="14.39" pos="48.98" lane="9/1to10/1_0" slope="0.00"/>
        <vehicle id="20" x="197.65" y="674.50" angle="0.00" type="DEFAULT_VEHTYPE" speed="23.94" pos="81.75" lane="2/6to2/7_0" slope="0.00"/>
        <vehicle id="22" x="803.96" y="981.65" angle="270.00" type="DEFAULT_VEHTYPE" speed="24.68" pos="73.29" lane="9/10to8/10_0" slope="0.00"/>
        <vehicle id="26" x="53.10" y="295.65" angle="270.00" type="DEFAULT_VEHTYPE" speed="22.81" pos="40.15" lane="1/3to0/3_0" slope="0.00"/>
    </timestep>
    <timestep time="78.00">
        <vehicle id="12" x="1.65" y="234.61" angle="0.00" type="DEFAULT_VEHTYPE" speed="21.16" pos="33.86" lane="0/2to0/3_0" slope="0.00"/>
    </timestep>
    <timestep time="81.00">
        <vehicle id="12" x="-1.65" y="280.82" angle="180.00" type="DEFAULT_VEHTYPE" speed="22.63" pos="8.43" lane="0/3to0/2_0" slope="0.00"/>
    </timestep>
    <timestep time="84.00">
        <vehicle id="12" x="-1.65" y="212.70" angle="180.00" type="DEFAULT_VEHTYPE" speed="22.71" pos="76.55" lane="0/3to0/2_0" slope="0.00"/>
    </timestep>
    <timestep time="87.00"/>
    <timestep time="90.00"/>
    <timestep time="93.00"/>
    <timestep time="96.00"/>
    <timestep time="99.00"/>
    <timestep time="102.00"/>
    <timestep time="105.00"/>
    <timestep time="108.00"/>
    <timestep time="111.00"/>
    <timestep time="114.00"/>
    <timestep time="117.00"/>
    <timestep time="120.00"/>
    <timestep time="123.00"/>
    <timestep time="126.00"/>
    <timestep time="129.00"/>
    <timestep time="132.00"/>
    <timestep time="135.00"/>
    <timestep time="138.00"/>
    <timestep time="141.00"/>
    <timestep time="144.00"/>
    <timestep time="147.00"/>
    <timestep time="150.00"/>
    <timestep time="153.00"/>
    <timestep time="156.00"/>
    <timestep time="159.00"/>
    <timestep time="162.00"/>
    <timestep time="165.00"/>
    <timestep time="168.00"/>
    <timestep time="171.00"/>
    <timestep time="174.00"/>
    <timestep time="177.00"/>
    <timestep time="180.00"/>
    <timestep time="183.00"/>
    <timestep time="186.00"/>
    <timestep time="189.00"/>
    <timestep time="192.00"/>
    <timestep time="195.00"/>
    <timestep time="198.00"/>
    <timestep time="201.00"/>
    <timestep time="204.00"/>
    <timestep time="207.00"/>
    <timestep time="210.00"/>
    <timestep time="213.00"/>
    <timestep time="216.00"/>
    <timestep time="219.00"/>
    <timestep time="222.00"/>
    <timestep time="225.00"/>
    <timestep time="228.00"/>
    <timestep time="231.00"/>
    <timestep time="234.00"/>
    <timestep time="237.00"/>
    <timestep time="240.00"/>
    <timestep time="243.00"/>
    <timestep time="246.00"/>
    <timestep time="249.00"/>
</fcd-export>
